<?xml version="1.0"?>
<!-- SCPlusV2_RS232 -->
<SBEDataUploadFile>
<ApplicationData>
<Seaterm232>
<SoftwareVersion>2.8.0.119</SoftwareVersion>
<BuildDate>07-Nov-2018</BuildDate>
</Seaterm232>
</ApplicationData>
<InstrumentState>
<HardwareData DeviceType='SBE19plus' SerialNumber='01907809'>

   <Manufacturer>Sea-Bird Electronics, Inc.</Manufacturer>

   <FirmwareVersion>3.1.8</FirmwareVersion>

   <FirmwareDate>Mar  9 2016 16:22:29</FirmwareDate>

   <CommandSetVersion>1.4</CommandSetVersion>

   <PCBAssembly PCBSerialNum='120721' AssemblyNum='41054J'/>

   <PCBAssembly PCBSerialNum='120715' AssemblyNum='41967A'/>

   <PCBAssembly PCBSerialNum='116699' AssemblyNum='41606'/>

   <PCBAssembly PCBSerialNum='120719' AssemblyNum='41059D'/>

   <MfgDate>28-Apr-2017</MfgDate>

   <InternalSensors>

      <Sensor id='Main Temperature'>

         <type>temperature0</type>

         <SerialNumber>01907809</SerialNumber>

      </Sensor>

      <Sensor id='Main Conductivity'>

         <type>conductivity-0</type>

         <SerialNumber>01907809</SerialNumber>

      </Sensor>

      <Sensor id='Main Pressure'>

         <type>strain-0</type>

         <SerialNumber>10586018</SerialNumber>

      </Sensor>

   </InternalSensors>

   <ExternalSensors>

      <Sensor id='volt 0'>

         <type>pH</type>

         <SerialNumber>27-0363</SerialNumber>

      </Sensor>

      <Sensor id='volt 1'>

         <type>ORP</type>

         <SerialNumber>27-0363</SerialNumber>

      </Sensor>

      <Sensor id='volt 2'>

         <type>OXY</type>

         <SerialNumber>43-0434</SerialNumber>

      </Sensor>

      <Sensor id='volt 3'>

         <type>PAR</type>

         <SerialNumber>1122</SerialNumber>

      </Sensor>

      <Sensor id='volt 4'>

         <type>ECO AFL/FL</type>

         <SerialNumber>FLNTURT-2496</SerialNumber>

      </Sensor>

      <Sensor id='volt 5'>

         <type>ECO-NTU</type>

         <SerialNumber>FLNTURT-2496</SerialNumber>

      </Sensor>

      <Sensor id='serial'>

         <type>not assigned</type>

         <SerialNumber>not assigned</SerialNumber>

      </Sensor>

   </ExternalSensors>

</HardwareData>
<StatusData DeviceType='SBE19plus' SerialNumber='01907809'>

   <DateTime>2019-06-24T17:08:01</DateTime>

   <LoggingState>not logging</LoggingState>

   <EventSummary numEvents='0'/>

   <Power>

      <vMain>12.9</vMain>

      <vLith>8.8</vLith>

      <iMain>63.1</iMain>

      <iPump>102.6</iPump>

      <iExt01>18.4</iExt01>

      <iExt2345>34.9</iExt2345>

   </Power>

   <MemorySummary>

      <Bytes>86618</Bytes>

      <Samples>3766</Samples>

      <SamplesFree>2857022</SamplesFree>

      <SampleLength>23</SampleLength>

      <Profiles>6</Profiles>

   </MemorySummary>

</StatusData>
<ConfigurationData DeviceType='SBE19plus' SerialNumber='01907809'>

   <ProfileMode>

      <ScansToAverage>1</ScansToAverage>

      <MinimumCondFreq>5</MinimumCondFreq>

      <PumpDelay>45</PumpDelay>

      <AutoRun>no</AutoRun>

      <IgnoreSwitch>no</IgnoreSwitch>

   </ProfileMode>

   <Battery>

      <Type>alkaline</Type>

      <CutOff>7.5</CutOff>

   </Battery>

   <DataChannels>

      <ExtVolt0>yes</ExtVolt0>

      <ExtVolt1>yes</ExtVolt1>

      <ExtVolt2>yes</ExtVolt2>

      <ExtVolt3>yes</ExtVolt3>

      <ExtVolt4>yes</ExtVolt4>

      <ExtVolt5>yes</ExtVolt5>

      <SBE38>no</SBE38>

      <WETLABS>no</WETLABS>

      <OPTODE>no</OPTODE>

      <SBE63>no</SBE63>

      <SeaFET>no</SeaFET>

      <GTD>no</GTD>

   </DataChannels>

   <EchoCharacters>yes</EchoCharacters>

   <OutputExecutedTag>yes</OutputExecutedTag>

   <OutputFormat>raw HEX</OutputFormat>

</ConfigurationData>
<CalibrationCoefficients DeviceType='SBE19plus' SerialNumber='01907809'>

   <Calibration format='TEMP1' id='Main Temperature'>

      <SerialNum>01907809</SerialNum>

      <CalDate>24-Mar-19</CalDate>

      <TA0>1.217923e-03</TA0>

      <TA1>2.816693e-04</TA1>

      <TA2>-1.603333e-06</TA2>

      <TA3>1.984146e-07</TA3>

      <TOFFSET>0.000000e+00</TOFFSET>

   </Calibration>

   <Calibration format='WBCOND0' id='Main Conductivity'>

      <SerialNum>01907809</SerialNum>

      <CalDate>24-Mar-19</CalDate>

      <G>-1.005893e+00</G>

      <H>1.268163e-01</H>

      <I>-1.515604e-04</I>

      <J>2.671373e-05</J>

      <CPCOR>-9.570000e-08</CPCOR>

      <CTCOR>3.250000e-06</CTCOR>

      <CSLOPE>1.000000e+00</CSLOPE>

   </Calibration>

   <Calibration format='STRAIN0' id='Main Pressure'>

      <SerialNum>10586018</SerialNum>

      <CalDate>11-Mar-19</CalDate>

      <PA0>4.565618e-02</PA0>

      <PA1>4.850951e-04</PA1>

      <PA2>-2.883271e-12</PA2>

      <PTCA0>5.252467e+05</PTCA0>

      <PTCA1>1.223042e+01</PTCA1>

      <PTCA2>-3.567450e-01</PTCA2>

      <PTCB0>2.516687e+01</PTCB0>

      <PTCB1>3.750000e-04</PTCB1>

      <PTCB2>0.000000e+00</PTCB2>

      <PTEMPA0>-5.487846e+01</PTEMPA0>

      <PTEMPA1>5.537568e+01</PTEMPA1>

      <PTEMPA2>-5.867271e-01</PTEMPA2>

      <POFFSET>7.140000e-01</POFFSET>

      <PRANGE>1.600000e+02</PRANGE>

   </Calibration>

   <Calibration format='VOLT0' id='Volt 0'>

      <OFFSET>-4.920000e-02</OFFSET>

      <SLOPE>1.248122e+00</SLOPE>

   </Calibration>

   <Calibration format='VOLT0' id='Volt 1'>

      <OFFSET>-4.784000e-02</OFFSET>

      <SLOPE>1.248871e+00</SLOPE>

   </Calibration>

   <Calibration format='VOLT0' id='Volt 2'>

      <OFFSET>-4.864632e-02</OFFSET>

      <SLOPE>1.248714e+00</SLOPE>

   </Calibration>

   <Calibration format='VOLT0' id='Volt 3'>

      <OFFSET>-4.743790e-02</OFFSET>

      <SLOPE>1.248571e+00</SLOPE>

   </Calibration>

   <Calibration format='VOLT0' id='Volt 4'>

      <OFFSET>-4.671263e-02</OFFSET>

      <SLOPE>1.248951e+00</SLOPE>

   </Calibration>

   <Calibration format='VOLT0' id='Volt 5'>

      <OFFSET>-4.871053e-02</OFFSET>

      <SLOPE>1.249136e+00</SLOPE>

   </Calibration>

   <Calibration format='FREQ0' id='external frequency channel'>

      <EXTFREQSF>1.000014e+00</EXTFREQSF>

   </Calibration>

</CalibrationCoefficients>
<EventCounters DeviceType='SBE19plus' SerialNumber='01907809'>

   <EventSummary numEvents='0'/>

</EventCounters></InstrumentState>
<Headers>

cast   4 24 Jun 2019 11:24:56 samples 1865 to 2491, avg = 1, stop = mag switch

</Headers><InstrumentRawData>
<SBEDataUpload startAddr='42872'>

   <Type>1</Type>

   <DataFormat>SEACATPLUS0</DataFormat>

   <Bytes>14421</Bytes>

   <Data>
FE8C03E1020B2A73081F4B239ACB85B8
83FFFFAC027F03FC8C03E5020B2A7308
1F4B169A4D84A183FFFFB1027F03FA8C
03E5020B2B7308204B1F9A3D858F83FF
FFB0027E03F68C03E7020B2B7308204B
1E9A82869583FFFFB6028703EF8C03F0
020B2A7308204B299A7786D083FFFFB6
027B03DC8C03F2020B2C7308214B1D9A
5783D883FFFFAC028003CD8C03EE020B
297308214B199A4981D083FFFFB6027C
03C68C03EF020B297308224B1A9AD081
AE83FFFFB4028003C28C03EE020B2A73
08224B2C9A3D847583FFFFAC028103C3
8C03EB020B2B7308234B169A1B87CE83
FFFFB2027E03C08C03EE020B2A730822
4B259A47B0DD83FFFFAF028003C08C03
E9020B2B7308244B129A3EA4D483FFFF
B2028203B78C03EE020B2A7308244B20
9A6189E083FFFFB7028103A48C03F002
0B297308244B219A688BDE83FFFFB402
87039D8C03F0020B2B7308254B1A9AA9
8BE383FFFFAC027C03998C03F0020B29
7308254B1F9A228CCC83FFFFB9028103
998C03F2020B2A7308254B0D9A498CCF
83FFFFAE027603988C03F2020B297308
254B149AD78DC783FFFFAD027E03968C
03F0020B2B7308264B119AAE8FC583FF
FFB0028203928C03EE020B2B7308254B
1E9A2CB1BB83FFFFB2027E038E8C03F0
020B2A7308254B1A9A46B1AE83FFFFEE
016A037E8C03F2020B2A7308254B299A
4BAAB483FFFFEC0172036E8C03F6020B
2B7308254B269A2FA8C783FFFFF3016E
03618C03F6020B2C7308254B1D9A52AA
DB83FFFFEF0172035E8C03F6020B2C73
08254B219ABFAFD083FFFFE7026A0458
8C03F6020B2C7308254B119AE8B3CE83
FFFFEE026504528C03F6020B2A730825
4B189A30B5E483FFFFEB026604488C03
F2020B287308254B189ACCA1E183FFFF
F2026604398C03F8020B287308244B17
9AFD8D0A84FFFFEA0266042C8C030903
0B297308254B1A9A4B8D0384FFFF0D03
FC02258C030B030B2A7308254B199A9F
B8EE83FFFF0E03FF021E8C0307030B2A
7308254B189A6AB8E383FFFF13030803
1C8C030D030B297308254B249A4282C7
83FFFF1503FB02168C0316030B287308
264B1A9ABD814B83FFFFB4027F03128C
030F030B297308264B219AFC80F982FF
FFB90283030D8C0307030B2A7308264B
219ADA829C84FFFFB90284030B8C0305
030B2B7308274B169A58854385FFFFAF
028203088C0308030B277308274B1C9A
7689C484FFFFB2027C03038C0305030B
2A7308284B1E9A1BB76384FFFFBA0283
03FB8B03FF020B297308284B209AC0B7
3C84FFFFB9027E03F08B03FF020B2973
08294B1A9A178A1984FFFFB4027E03E3
8B03FC020B2A7308294B219A1B861684
FFFFB3028303D28B03FF020B2B73082A
4B219A0685A783FFFFB1028303C58B03
01030B2E73082A4B289AA9838B8CFFFF
AE027E03B98B03FF020B4673082A4B16
9AAA82978DFFFFAE028103B08B03FC02
0B7373082A4B1E9AF0889F8EFFFFB402
7E03488B0372040B0C7408294B1B9A30
B83893255DC202AB034A870329060BDC
74082A4B1D9A52B8479ACE63BA02B803
0182038D070BE475082A4B209A1AB806
A12966C102B2034F7E0390070BBF7608
2A4B119ABAB091A5C266C302B103A97C
038E070B7277082A4B1E9A0198C6A8F3
66570352042E7D038C070BD477082A4B
429A54ADF2AA616757035304DE7E038C
070B3278082A4B879A1B9168AC8B6753
034F04E780038C070B9C78082A4BE09A
6D855DADBA6752035504C082038B070B
E178082A4B5B9BE684C8ADA767FF0334
042A84038A070BFC78082A4BC09B6D84
DEADB3670204320418850388070B0D79
082A4B169C0684EDADB367FE032E0494
850388070B1B79082A4B679C2D84D1AD
AF67FD033504D3850388070B1579082A
4BAB9C1A84B7ADC6671D043304188603
85070B0C79082A4BD09C4384A4ADE467
210433044D860388070B0479082A4B03
9D908473AD07681D0430046886038A07
0BF578082A4B059DAE8431AD05681D04
2E0429860392070BEA78082B4B399DCF
84E6AC006809042004A88403AE070BE3
78082B4BE99CE484A3ACF46710041E04
488203C5070BDB78082B4BB39CF0846F
ACFD670E042004278003D2070BDA7808
2C4B9C9CED844AAC09680F0421048E7E
03D7070BDA78082C4B259CF08408AC16
6805042404827D03D8070BD778082C4B
759B0485CEAB07680C042004EC7C03D4
070BD878082C4B9E9AF8849DAB1C680B
042304867C03D2070BDB78082C4BE599
F68476AB12680E041D04247C03CE070B
DE78082C4B119907854CAB1C680C041D
04D87B03CE070BE278082C4B4998D984
1EAB2B68FA032D049A7B03CD070BE378
082C4B6397C784ECAA366802041F046D
7B03CE070BE278082B4B91964F84B9AA
3068FB031D046E7B03C9070BE378082C
4BA9951B847BAA3168FE032304827B03
C7070BFA78082B4B0A95168457AA3968
F6031F04AA7B03C7070B1F79082B4B7E
942F833AAA3C68FC032304F17B03C707
0B3579082C4B2D94D08222AA2968FD03
1D04357C03C5070B2D79082B4BED9350
841AAA3668FF031F046C7C03C5070B1B
79082B4B8793888406AA4368EB032B04
877C03C3070B1A79082B4B05935E83FE
A94668EB032E04947C03BD070B377908
2A4B61924383DFA93E6BED033304C77C
03B8070B6C7908294BCA912482EFA957
6BED033204407D03B2070BBD79082A4B
16910480E3A9706BF0033304DF7D03AE
070B097A08294B7F90DF7C97A9826BE5
032A045D7E03AE070B327A082A4BE58F
717A2DA9936BE6032F04B87E03AC070B
3A7A082A4B908FCA7BE8A8896BF20332
04F97E03AC070B307A082A4B0890087C
D3A8916BE10336042D7F03AA070B2F7A
082A4B1F917D7CC6A8876B23042C044D
7F03AA070B377A082A4B6692BD7BB9A8
826B24042404357F03A7070B427A0829
4B4C93EE7AB1A8856B20042C04097F03
A7070B477A082A4BE5937B7A94A8806B
21043304037F03A7070B417A082A4BFD
93247A7DA8856B24041F041C7F03A507
0B407A082A4B9B93CB7958A87F6B2004
1C04677F03A5070B497A082A4BE79233
7A3DA8826B1A042004DE7F03A5070B58
7A082A4B29928B7A23A8826B1D041C04
4D8003A3070B637A082B4BCC91107A01
A87A6B20043504AF8003A1070B6B7A08
2B4B92917B79E9A7776B1C043004E680
03A3070B707A082B4BA6913B79D7A77C
6B1C042E040C8103A1070B757A082B4B
0892F779C1A76D6B21042E041F8103A3
070B767A082B4B8092F27992A76F6B30
042104388103A1070B767A082B4BFF92
287A75A7616B30041F04588103A1070B
737A082B4B8E93307A55A75F6B300422
047981039F070B6E7A082B4B1594427A
3DA7556B2A041F04AB81039F070B6C7A
082B4B8E94797A31A74F6B23042C04E3
81039F070B697A082A4BFE94E07A19A7
486B240432042B8203A1070B6E7A082B
4B73952C7AFDA6426B1F042F04D08203
9F070B717A082B4BA195F379E2A6426B
220432046E83039D070B6E7A082B4BC6
95127AC9A63B6B1B042C04AA83039B07
0B6C7A082B4BE8956B7AB9A6326B2404
2904E083039D070B6B7A082B4B1C9608
7BB5A6316B1B042B0444840399070B6B
7A082A4B56963F7AB1A6316B18042E04
B084039B070B6E7A082A4BA69676799D
A62F6B240431040085039B070B6E7A08
2B4BCF9672798BA6226B1C0418046185
039B070B6D7A082B4BD496437B76A61D
6B1E042204F485039B070B6C7A082A4B
AA967C7A54A6206B26041E04B9860399
070B6C7A082B4B4F96427A40A6116B21
042104B1870399070B6D7A082A4BBC95
717915A6066B0E041E04BD880396070B
6E7A082A4B0D95FE7904A6026B0E0422
04A5890396070B707A082B4B55949878
DFA5026B0B0426044A8A0396070B737A
082B4BA2937C79DCA5FB6A10042104BD
8A0394070B737A082B4B04934B79C7A5
F76A1B042504FB8A0396070B707A082B
4B7B928079BCA5F36A1F041A04FC8A03
97070B707A082B4BDD91F879A5A5EF6A
1D041D04DF8A0396070B737A082B4B3F
911B7A82A5E46A20042204D38A039907
0B757A082B4BAF90FD7973A5EA6AFA03
2404DD8A0399070B767A082B4B1B9012
7961A5DF6AFE032204FD8A0396070B75
7A082B4B758F9E783DA5D76A02042404
258B0396070B787A082B4BCF8E97781C
A5D66A01042304538B0397070B777A08
2C4B188EC87808A5CD6A21041E04758B
0396070B767A082B4B778D8A79F5A4D4
6A1B041B048E8B0399070B727A082B4B
D08C317AD8A4BD6A1B0421048B8B0399
070B6A7A082B4B198C8779C3A4BD6A1E
042004658B0396070B797A082B4B638B
6A78B9A4C16A1B041F04618B0396070B
A47A082B4B988AF776B0A4D66A090422
049B8B0395070BBE7A082B4BDF89E876
5CA4C36A0E042104AA8B0394070BB37A
082B4B4D89287710A4C36A0C042504A8
8B0394070B987A082B4BD7881277F9A3
C06A0E041F04ED8B0394070B8D7A082B
4B54883777F5A3B46A20041B04328C03
94070B997A082B4BD287D675F7A3AE6A
19041B044A8C0396070BA57A082A4B38
870F76F8A3B66A1B042804578C039507
0BAC7A082B4B8E862E76E7A3A36A1F04
19045E8C0394070BA77A082B4BE485B2
76CCA3A56A23041F04748C0392070BA2
7A082B4B3E854B76B4A39F6A1E041D04
918C0394070B9C7A082B4B97847C769D
A3926A1F041D04A68C0394070B9D7A08
2B4BEE83707684A3946A1C041E04A48C
0397070B9E7A082C4B2E83517672A389
6A2E042104938C0394070BA17A082C4B
8082A67550A3846A30042204808C0394
070BA37A082C4BDB81AA753DA38E6A32
041F046C8C0394070BA57A082C4B3C81
AB7625A37B6A32041F045E8C0396070B
A77A082C4B93806F760EA37E6A350426
044A8C0394070BA97A082C4B05803476
EEA27A6A36041F043C8C0397070BA97A
082C4B597F6976CBA2756A3304210430
8C0396070BA47A082C4BC37E8A76A5A2
6C6A2B041904288C0396070BA17A082C
4B347E527793A2656A2F042304248C03
96070BA37A082B4BA67DB0768CA2636A
26043004188C0394070BA57A082B4B25
7DD4757DA2656A23042F04FF8B039407
0BA87A082C4BB27C9B755FA25F6A1F04
2E04E68B0397070BA77A082C4B297C20
7655A2586A1E042F04C98B0392070BA3
7A082B4BB87B5B7641A2576A1F043304
B18B0394070BA27A082B4B397B5C762E
A24C6A21043604988B0394070BA77A08
2B4BD27AA67529A2566A20043704808B
0394070BB07A082A4B687A5B7620A24B
6A1F043904688B0394070BB67A082B4B
FE791C7611A24C6A23042604558B0395
070BB77A082B4B91797E7608A2416A1C
041F04488B0394070BB47A082B4B2D79
4D7600A2476A1F041F043F8B0394070B
B27A082C4BD378F276ECA1386A200424
04388B0394070BB07A082C4B71784076
E2A13E6A3D0421042D8B0394070BAF7A
082C4B3678A875CCA1326A3F04290420
8B0394070BB17A082C4BD6777B76B2A1
306A45041D04118B0395070BB17A082D
4B96772477ABA1346A40042404048B03
94070BB07A082D4B5077EF779AA12B6A
41042004F48A0394070BAD7A082D4B15
77847899A1296A3E042304E78A039407
0BAA7A082D4BD87639798CA1216A3F04
2704DE8A0394070BAD7A082D4BA87620
798CA11C6A43042004D18A0395070BAD
7A082D4B69762E797DA11A6A3A041D04
C28A0394070BAE7A082D4B337621786D
A1106A1A042404B58A0394070BAE7A08
2E4B04761C785DA10F6A1B041B04A98A
0394070BB07A082D4BE2757F7855A112
6A1F0426049D8A0394070BB07A082D4B
B27596784CA1046A1F041F048D8A0394
070BAF7A082D4B9075587940A1046A38
041D04878A0388070BAF7A082D4B5B75
857940A1076A3D041D04F38C037F070B
AF7A082D4B5B75BD7838A1F6693F041B
04C1930381070BB27A082D4BD677F478
38A1FF69410423046D990381070BB17A
082D4B747E2F792DA1F36940042104CF
9C0381070BAF7A082C4B7C87A67824A1
EF693A041D049D9E0383070BAC7A082C
4B8790B0771AA1F6693A0423048B9F03
84070B9C7A082C4B08994A7721A1E969
3B041A04BE9F0383070B8D7A082C4B52
9F5B77BDA0E36952043104779F038107
0B8F7A082C4B5AA46C762EA0E3695504
2E04D49F0381070BA27A082C4B68A863
761BA0F1695004310458A00381070BA0
7A082C4B73AB65751FA0E1694A042C04
AAA00381070B9A7A082C4BB2ADA87539
A0E0693E042604C4A00382070B9C7A08
2C4B6CAF187A3EA0EB693B0420047CA0
0383070BA37A082C4BA6B0AB7F32A0FB
6941042404B89F0383070BA17A082C4B
A3B1027E1EA0FF693F041E04079F0383
070B9C7A082C4B44B2F87C12A0056A40
042204FE9E0383070B957A082B4BCBB2
3C7912A0086A3C041F04379F0383070B
967A082B4B2BB3627710A0056A450421
04979F0384070BA77A082B4B7EB34D74
04A0076A47041B04DC9F0383070BC37A
082C4BB6B33673F09FFC693F041B04F6
9F0383070BDC7A082C4BF8B37B75D79F
FD693E041B041BA00383070BE07A082C
4B32B4BD70A89FF3693C04220451A003
81070BC77A082B4B62B46370879FED69
3C041A0463A00383070BA27A082C4B89
B4C36D6F9FE1693A041D0400A0038207
0BA07A082C4B9FB4546F5A9FD8693B04
1D04A29F0381070BB47A082D4BBBB429
723F9FD9693D041A04A79F0383070BA8
7A082D4BD6B4C974319FD16941042504
AE9F0388070B6A7A082D4BECB4AF7D08
9F80653D041B04209D038A070B207A08
2D4B1FB50E7CD59ECB6539042304CB99
0388070B157A082D4B6EB5A77DA49EF7
653F04200422980386070B1E7A082D4B
D0B569807E9E356643041F045F980388
070B047A082D4BDDB54B82489E41663F
0424049897038E070BA679082D4B9DB5
2084219E4F663B041504B594038C070B
FD78082E4B68B5C485EF9D5C66460428
0414910390070B7578082D4B2CB53386
C09D696641042604428D0391070B2F78
082D4BF8B402878E9D6A6643042204F7
890392070B4578082D4B83B488836D9D
6C6638041A04D8870390070B8878082D
4BF1B389832F9D5C66FB032804FF8603
90070B9D78082D4B52B3F283029D6166
FA032E044A870390070BAC78082C4BC2
B2ED82D89C6866FB0335041488038C07
0BBC78082C4B34B20D83B29C8666FB03
2A04E888038B070BAF78082C4BB6B188
838A9C9666090421046D8A038E070B8E
78082B4B51B1BF815A9CB0660C041D04
A88A0390070B6178082C4BFEB09E8236
9CB8660F041E047E890390070B3D7808
2C4BD5B0EE96189CBA660F041E042B88
0390070B3878082C4BEFB033B1059CD6
66EE031C0434870390070B4978082C4B
03B1D4B3D89BE866E903190415870391
070B6778082C4BEAB057B4899BE666F4
0320040587038E070B7E78082D4BBEB0
1BB44B9BF266F6031F044488038A070B
9B78082D4B79B0E6B21F9BF266F00330
04348B038A070BB678082D4B44B0C48F
F49AFA66EE032C04158E0388070BCB78
082D4B13B02790E39AFB66EB032E0417
910388070BD278082D4B15B00DAEBF9A
FB66F4033504E3940388070BD378082D
4B1FB04BB49C9AFC6603042004A19703
85070BD478082D4B46B003B4879A0467
02041F0475990388070BE678082D4B9B
B0E2B36E9A0B67FA032204559A038807
0BF578082D4B0EB177B4589A1667FA03
1E047D9A0385070BFB78082D4BA2B1CF
B4429A0C67020419049B9A0385070BF5
78082D4B3FB2ABB4269A0B672F041D04
609A0389070BF178082E4BD3B28AB413
9A0E672B0422046B9A0385070BF97808
2E4B53B336B4FC99026727041C04E69A
0385070B0A79082D4BB8B325B4DC9910
672E042404EC9A0385070B1879082C4B
FEB328B4C7990767220424049F9A0388
070B2079082C4B4DB4FDB399990F671B
041A042E9A0388070B1879082C4B61B4
96B37999156720042204BA980389070B
1479082C4B5FB433B265990C671D0422
0406970388070B3879082C4B55B45EAB
4C9903672C04220438960385070B6379
082C4B5DB44DA41D99F66630041F0476
960385070B9A79082B4B63B4F19DE998
F8663004240490960383070BD779082C
4B3AB4C4A9C598FD6824042204CA9603
84070B1F7A082C4BEBB31193AE982669
3B042F0450980385070B707A082D4BB2
B3288EA498426945042D042B9A038307
0BB27A082D4B46B3B08E8B9866694304
3104259C0383070BFB7A082D4BEFB24B
8B6E98756940042B04FF9D0383070B46
7B082C4BCFB2EE885D988A6952044004
5E9F0383070BA27B082C4BECB2278748
9894694E04400412A00384070B087C08
2C4B4FB316853798A66952044604BBA0
037F070B7F7C082C4BD5B3DF7F1598BA
6950043E049BA1037F070B2C7D082C4B
39B4B57BFC97CB694E043D0495A2037F
070BAD7D082C4B80B45377E797C06962
04330487A3037B070B1C7E082C4B95B4
4D77D097C96961042C0449A4037B070B
927E082C4BB0B4E776C397C6695B0431
04F5A4037A070BC17E082C4BC8B41E76
A797C9695C04330466A5037B070BD87E
082C4BDFB45476A197C4698E043104A5
A50379070B307F082C4BC3B487769097
B76992042E04E1A50377070BEB7F082C
4B9BB47C767097B3698A04330472A603
70070B8780082C4B5FB470765297AB69
90042B0483A70370070BF680082C4B16
B49F762D9793699C043F0486A8036E07
0B6E81082C4BBBB3EF760C976E699B04
3E046AA9036E070BE281082C4B29B362
77F5965069A0043D0475AA036C070B56
82082C4B66B29F77D7963D69A6043E04
59AB036C070BEF82082C4B68B1E677C0
961F69EF0427049DAC036C070B8E8308
2B4B94B0C977A6961069E904330407AE
036C070BE883082C4BA4AF9A77869609
69F004370441AF036B070BF183082C4B
80AE19777896F468F0043304E8AF036C
070BE483082C4B77ADE5767096F26801
053704C8AF036C070BEA83082C4B59AC
19775F96DB68FC042E0436AF036C070B
5184082C4B48AB40775096C768F90437
04C4AE036A070B0385082C4B81AA7877
3996CC680605310421AF0372070B6C85
082C4BD5A9CD772396BD6802052E046F
B00374070BA885082C4B54A9E0771696
A9680205310498B10372070B0F86082D
4B13A9D3770C9692680205280437B203
74070B7C86082D4BB2A8EF77FF958A68
FF043104BBB20377070BBC86082D4BE2
A7E177EC957268000532046CB3037907
0BEA86082D4BBBA6BF77E09566680105
2904E6B30379070B2187082D4B8CA5A0
77D4955968FC042E0424B4037A070B60
87082C4B9AA4A977BF956368FA042B04
43B4037B070BA187082C4B48A4BE77B2
954368FE04350462B4037B070BDF8708
2C4B33A4DE779C954168010531047FB4
037D070B3288082C4B46A40D78879540
68FB042C04C5B40377070B7C88082C4B
5BA429787D953C68FB042B0479B50374
070B9A88082C4B6AA4437872953B6800
05310403B60376070BB288082D4B91A4
567867952D68F10434043AB60379070B
C588082D4B25A57D786A952968F0042B
0429B60377070BCE88082D4B48A66578
62951C68ED042E0401B60374070BDF88
082D4B8BA767785C951A68EF0426040A
B60374070BF388082D4B9BA85F785C95
136834052F0437B60372070B0A89082E
4B80A96C78529511683105350474B603
74070B2089082E4B16AA507853950468
33053104A0B60372070B2989082F4BA6
AA61784795056827053004CAB6037207
0B3A89082E4B2EAB56784595FB672A05
2E04EBB60370070B5689082F4BC8AB56
784895FC670F052D040CB70370070B80
8908304B3CAC51783A950A6814052E04
45B70369070BBB8908304BA1AC5C7833
951C6810053504CDB7035F070B038A08
304B01AD677824951D680F052A04B8B8
035D070B4B8A08304B31AD657816951A
686B05330490B9035F070B788A08304B
5CAD577810955A686F05330411BA0361
070BA88A08304B58AD4F7813956B686E
05280419BA0361070BF88A08314B25AD
6B7802955E6872052C0468BA035F070B
518B08314BC8AC5E78EF9454682D053D
0400BC035F070B7F8B08304B62AC4F78
EA9453682E0539043DBE035D070B9E8B
08304BFEAB4978E1944A6834054304D9
BF035D070BC18B082F4BB8AB4378DF94
4B6829053B046AC0035F070BE58B0830
4B43AB3A78E494456877054A0461C003
5D070B1C8C082E4BD0AA4278DA943968
700552049EC00357070B5C8C082E4B65
AA4578D5942D686E0557040CC2035207
0B918C082E4BD7A93A78C2942A686E05
4D04C7C3034E070BAC8C082E4B55A945
78BA9415684D05530459C5034C070BC4
8C082E4BF9A84C78C594146851055504
AFC6034C070BE18C082E4B8FA85178BF
9414684D055604CEC7034C070B048D08
2E4B43A85978B994076850055504A0C8
0350070B398D082E4BECA76C78B094F8
671405530400C9034E070B778D082E4B
B6A76E78A894E16708054F0433C90348
070BB38D082E4B95A77B78A194DA670D
055304C9C9035B070BE78D082D4B67A7
74789594C86712054A04A0CB036C070B
1C8E082D4B3CA777788E94C267120551
048FCD0370070B4D8E082D4B0EA77B78
8494B7670B053E044FCF037E070B838E
082D4BD0A689787894B6670A053B0446
D10366070BC78E082E4B9BA679786A94
B56716053F0497D30357070BF58E082D
4B4DA681784A94B1670A053904B1D603
59070B0F8F082E4BE1A583784394A667
0C053F0461D9035F070B228F082E4B5A
A57E784094A0670D054004C7D9035F07
0B398F082E4B07A58C783B94A0670D05
3E0485D9035F070B5B8F082F4B13A58F
783D948E670B053B043FDA0359070B8A
8F082E4B7BA5A4783694836724054204
11DA035B070BC78F082E4BF8A5BB7836
9486671D05390494D9035B070BFF8F08
2E4B98A6C27838947C67220541047DDA
0361070B2990082E4B27A7BD7844946E
672205400449DD0363070B4B90082E4B
7BA7D17841946667010542042DE10365
070B6790082E4BB4A7CB7843945767FE
043E0452E40366070B8190082E4BADA7
BC783294446700053C043AE60366070B
9C90082E4BB8A7CC7833943E67FE043E
0439E70361070BB590082E4BDAA7CA78
36942C67150546043BE70363070BD390
082F4BE6A7B17828941F6718053E0424
E70361070BF090082F4BE6A7B9783194
0E670F054004B1E50361070B10910830
4BC7A79C78289407670B053D04E8E303
63070B2A91082F4BAFA7897825940367
110539049BE30361070B509108304B71
A780782594016710055104EFE3036307
0BA791082F4B2DA779780D94F4661105
4B0479E6035B070BF191082F4B1CA763
78FA93F66611054D04CFEA035B070BFF
9108304BD7A64978EC93FB6611054E04
7FEE0361070B089208304B99A63278E7
93FD6672057A04F7EF0361070B249208
304B56A62178ED93EF6670057E042EF0
0352070B6392082F4B14A62578E493EE
666B057804DDF10346070BB492082F4B
D2A50578D693E8666D0573043BF40344
070BE69208304B62A5EF77D193E966B6
05600457F6033F070BE99208304BFBA4
D677CC93E566B5055904B4F80344070B
ED92082F4BA0A4CA77C993EC66AF055D
04ADFA0341070B1393082F4B6CA4A677
C393DF66AD0558047CFB0341070B4093
082F4B76A49E77CD93E1667F055D04B1
FB033F070B6E93082F4BC2A48677C193
D6667D055F04DDFB033B070B8D93082F
4B37A56C77C693CB668705580490FD03
41070B9993082F4BC0A55677BE93C666
7A0557045FFE033E070BB393082F4BA3
A63F77BC93C166BB05720498FF033B07
0BD493082F4BF9A73B77B693B866BE05
6B045601043D070BF593082F4B97A929
77BA93B466C1056D04C702043D070B18
94082E4B32AB1077C693BA66BE056E04
FD03043B070B4F94082E4BA2ACF476C7
93AE66B7056B04CF050437070B859408
2E4B11AEEB76C693AB6608066704C108
0431070BAD94082F4B75AFE376B993A9
6606066904250C0433070BD094082F4B
95B0D876AF938F6606066B04080F0430
070BDF94082F4BD7B1D1769E939666FF
0568049B100430070BE394082F4B4DB3
DA76A9939466B605640452110430070B
EE94082F4BD5B4DA76A4938A66A9056A
0424110435070B1195082F4B80B6D376
A4938466B2056B044C100433070B3F95
082F4B36B8CC76A4938066AA056804F7
0F042D070B6E95082F4BDFB9C176A393
7C669B056504C012042A070B9295082E
4BF2BAC276A7937E669D056604DC1504
2E070BB095082F4B9BBBC576A2939266
A3057104C715042A070BBF95082E4B15
BCC3769893A766A7056E047916042607
0BC595082E4BD8BC987695939766A205
5904EC180428070BDB95082E4BD3BD9B
76989398669D0560040A1B0427070B18
96082F4BD8BE71769B939D669C055704
2D1D0417070B7B96082E4BC8BF2D7690
938F66A2055F042A240415070BCA9608
2E4BAAC01A767E938C6692055804B92D
0415070BF196082E4B2BC1FE75739385
668E055904D0350417070B1297082E4B
9DC1D9756C93876690055F04233A0415
070B3497082E4BACC2CA757C9387668E
055C04B83B0416070B5C97082E4B86C4
A8757C937D668F055804AC3D0417070B
9797082E4B3EC67F757E93716663054C
0471410419070BD197082F4BC3C76075
7A9369665C054D04FB440419070BF897
082E4BEEC863757493536660055604A1
470417070B1998082F4BD1C94A756F93
4366640553047148041D070B4298082F
4B58CA32756A933B6631054C04334A04
1F070B6F98082F4BA8CA2B756A932066
30054D04D14C041D070BA798082F4B99
CA097562931C662F055104F64E042207
0BD998082F4B7ECAFD746193F5653105
4F042E530426070BF698082F4B74CAF4
745793E3651005360414580422070B11
99082E4B24CAE5745A93D9650B052A04
D8580424070B3F99082E4BBAC9BF7451
93B5650D052D04A658042D070B789908
2E4B23C9AD744593A2650D052C04BD5B
0435070B9299082E4B1DC894743E9399
650E05310455630433070BA899082E4B
C7C66474349381650D052C04EE670433
070BE899082F4B6EC546743993736510
053304AD690444070B3A9A082F4BC9C3
02742A93656509053204946E0457070B
839A082F4B29C1BD7322935A6551052C
041F770459070BB19A082F4B50BDBF73
12933A6551053504EA7E0457070BD19A
082F4B4CB9B7730A93296550052B044D
82045B070B009B082F4BA1B494730E93
18654D0531046D85047D070B3D9B082F
4B2AAE5C730A930C6549052D04CD8C04
99070B789B082E4B2EA63273F7920965
85054304899404C1070BB69B082E4B74
9D0373E992EF6478054404439A049A08
0B059C082F4BF493D572D992DC648005
42040DA304B7090B6B9C082F4BD58A84
72C392D8647D053D043FAB042C0C0BD5
9C082F4B7A802672A392E3645F054204
37B3045D0E0B239D082F4BA875FF716C
92D66466053F04FFBA04480F0B469D08
2F4B266AED713892806465054404D1C0
04FB0E0B629D082F4B2E60B0710C9285
645B05410429C304750F0BA49D082F4B
F0565B71D3918564EE04500495C304A9
130BF89D082E4B284E0C7177919264ED
04550477C60436170B359E082E4B3D47
F7701B913E65F8045104DDCA04B0170B
449E082E4BFD40EC70CC90E565F10453
04E5CE0469170B519E082E4BDD3BCD70
81909E669704870415D104FA170B649E
082E4B1238CF704B9023679E0489046A
D20473160B6F9E082D4B9234CC700C90
8467A20488047DD20442150B779E082D
4BE931D670E18FC2679D048E047ED104
06150B809E082D4B892FD570AA8F1868
C10466043DD004DD140B899E082D4BAB
2DCE70768F6368BB04660437CF04B214
0B8E9E082C4B2A2CDB70258FC068BF04
6E0452CE04E3140B989E082D4BE62AE7
70B58EFC68C3046804C8CD0436140BA2
9E082D4BDB29FD70428E4669A0048D04
C4CC0477130BAB9E082C4B06290C71DE
8D8D69A2048604D4CB04D3130BB49E08
2D4B4D2819717F8DCC699A047C04D6CA
0414150BBB9E082D4BC4272671188DF6
699C0485042FCB0401160BBE9E082E4B
3D270671C68C2A6A5D04B80496CD0404
160BC29E082E4BF1260171658C686A60
04B20438CF04C2160BCA9E082E4BB826
0D71148CA86A5B04B8044DD104BF170B
D19E082E4B8D260871B48BE66A5904BB
044DD40442180BD59E082F4B6826FB70
578B096B3B04D80483D5045D180BDA9E
082E4B4B26E070068B0C6B3604D60403
D60419180BD79E082F4B1426CE70AC8A
716B4504DB043FD6040F180BD89E0830
4BD825D270678A416C3D04D804E1D504
CF170BDA9E08304B9A25BE701B8AF96C
4104E804ADD50472170BDA9E08304B51
259D70CF89786D4104F004C3D4044A17
0BDA9E08304B0D2582708C89E16D4404
EE04A9D30452170BDC9E08304BC32479
7049895F6E4004E704DDD2043D170BDD
9E08304B8D2487700689E26E4404E504
8ED2043D170BDE9E08304B4D247370C5
88786F57040505B4D304AA170BDD9E08
304B21246070988813704E0404058FD4
04FC170BDD9E08304BF52354705F88E6
7053041105C2D404CB170BDA9E082F4B
D7233E703488B07155040805E1D404F6
160BC29E082F4BBA23A06F0488DB7375
04E90435D404E5150B9C9E082F4B9D23
396FC7872B736F04E504C3D0048D160B
589E082F4B78238E6F9F87A7727304E6
04BECC04C9160B2A9E082E4B5123946F
668795726C04EE04A8C9049C170B3D9E
082F4B4223B96F45876572FC04C70496
CB04FE170B589E082F4B3823956F3087
12720205C7041ECF04FC160B709E082F
4B2B23916F1F87D7710205C304D9D004
97160B8A9E08304B2923A26F1E87D071
0205C90470D1042F160B989E082F4B31
23B56F1C87B2719D04C70437D1044116
0B9E9E082F4B2E23AC6F28879A71A704
C6040FD104BA160B799E082F4B0F23DC
6F1B878471A604C90492D10437150BE2
9D08304BE522B0702E87B1719B04C304
12D00461130B259D08304BC322D17043
87A6719404EB0422CB0463110B039D08
2F4B9A228770478785719304E504BBC3
04DD120B509D08304B82228D70508733
719504ED04B3BF0436140B889D08304B
6A22C370578733719404E30454C204E9
130B3D9D08304B8A2272715387117196
049504D4C40458100B6A9C08304B1023
347261872371A0049304CAC004E80D0B
A89B08304BCC2384727987F8709D0499
0467B704E30C0B739B08304B75245B72
868700719E04970411AE04190E0B989B
082F4BDF2450729287EA70E30479044F
A904210E0BCB9B082F4B84254E72A687
C970E3047504E4A904590E0BB49B082F
4BF826B872BC87D96FE10479046DAB04
2C0D0BFF9A082F4B1729C073D1871E70
DA047C046FAB04D20B0BE099082E4B8A
2B8D74F687E96F1505660402A804510B
0B3199082E4B032E7C741688C06F0B05
680468A1041B0B0B2C99082D4BB82FA7
742C88CA6F18056904269C04010B0B6B
99082D4B1A319A7442881B6F0F056B04
E19A047B0A0B8299082D4B6832AA746D
88C06E0F0568048A9A047C0A0B299908
2E4B5D3434758788C86E55053F04F999
041B0A0B4898082E4BC836F475B288B0
6E49054004E3970451090B7197082E4B
1E391776CE88706E4D054404379104A6
090B3E97082E4B2C3B0476DB88566E53
0540045E8B0462090B5D97082E4B273D
ED750089176E4005390429880435090B
8297082D4B5E3FDE750D89E96D3D053E
04D1860424090B6197082D4B11420B76
1D89A66D3A053B04A2880411090BD396
082E4BA64594763D89856D3C05450420
880424090BEA95082E4B814928775489
426D30053F0443860411090B4395082D
4B454DF5767489246D2B053C04DD8304
0E090B4C95082E4BDC50E5767B895F6D
31053A04EA800456080B8595082E4B9E
53CA768989396D28053B04027B044508
0B8E95082E4B5356D3769789016D4505
4004E075042D080B4095082E4BF8582A
77AB89E66C4B053E0438720498080B87
94082E4BCE5BB977BD89046D39054004
CA7204B9080B9793082E4BD65FDC77D3
89F26C3E053E04217504A7080B329308
2E4B2664C077D889D96C4D053B049175
0478080B4393082D4BCB68CD77DE89C6
6C52054404F07304F4070B7393082D4B
BF6CD277ED89F36C53053D04D36D04B4
070B7F93082C4BA56FDE77FB89D16C4D
053B044D6504BE070B2E93082C4BF871
1378068AC26C63054F04095F040B080B
4E92082C4BF87351781F8ACC6C630552
04E55F042B080B4C91082C4BED763D78
308A9F6C60055304AB62042B080BF890
082C4B007B3A78238A836C6305550488
630430080B0F91082C4BC87F6F781E8A
766C610552048A6304E7070B4891082B
4B428477781F8A546C85055E04656104
C7070B3F91082B4BB4875F78218A386C
83055904845D04D0070BAC90082B4BC6
897278388A276C830561040E5B04F807
0BB08F082B4B268B7F78488A086C8305
5E04E65A04D0070BF18E082A4B898C60
78508AE56B90055504C45904DF070BE0
8E082B4B0D8E81784C8A0B6C90055804
385704B6070B1F8F082A4B1990BB7844
8A506C90055E04705104A1070B498F08
2A4BC391BE784B8A2C6C93055904EC47
047F070B238F082A4B77937F78548A1D
6C09054D04473D04A3070B718E082A4B
2095C878678A566C0C055004A53A04B6
070B568D082B4B0A972B797D8A356C13
055304013F04AC070B998C082C4BBD98
EF787D8A276C0E0553040F4204A5070B
918C082C4B7B9A00795D8A256C120542
04B2400481070BD18C082C4B249C1579
568A3D6C09053F04B4380470070BE88C
082B4BAA9D2B79568A246C0D053D0402
2D0470070BA48C082B4B1F9F37795D8A
0B6C0C053F04D1230485070BDE8B082C
4B78A03579778A156C05053104CD2204
8C070BC68A082C4BBCA10C798D8AFE6B
FB042A04112A0488070B1E8A082D4B9D
A2D778908AE76BFC042B04EE2D048307
0B208A082C4B27A32E79888ADC6BFE04
2A04382D047F070B558A082C4BB8A355
79888ADA6BFD042904BA29047F070B55
8A082D4B75A44F79848AED6B53054B04
45250477070BC689082D4B5CA5677992
8A076C4F054D04EE1F046C070B988808
2E4B37A63A79A18A0C6C4D054F042D1E
0470070B8E87082E4B09A7FB78BB8A1E
6C49054B04781E0470070B6287082E4B
7BA72B799C8A3D6C3C0553044D1C0463
070BA687082D4BC1A75179888A516C3C
054F04E70F0463070BDE87082D4B4FA8
22797F8A5C6C3E054F043A03045F070B
DE87082D4B9FA9DF78788A4B6C36054F
0493FA035F070BA287082D4B90AAD778
7D8A496C830551045DF20363070B1387
082D4B33ABBF789F8A666C7E054F0425
F00366070B3586082E4B52AB7978BF8A
656C83054A042EF80363070B6385082D
4B0EAB2778CD8A5F6C81054A045B0004
63070B0B85082C4B51AAFE77D28A526C
5C054504EC030461070B1A85082C4BCD
A93278AA8A396C63053B04E401045F07
0B5C85082D4BA6A92578998A1A6C5B05
40045CFB035D070BAB85082D4B0EAA1E
789B8A0C6C5F053E043AF2035F070BD4
85082D4BD6AAFD77A28AFA6B90054704
A3E7035B070BEC85082C4B87ABE577AA
8AE66B91053F0464DF035B070BFF8508
2C4B04ACCB77BD8AD46B96053E0413DF
0359070B1886082C4B4BACB577BD8AC2
6B8D053B048AE0035D070B3C86082D4B
22ACA777C08AAD6B8E053E04CADA035F
070B5186082D4B12AC8D77BD8A9F6B8D
05410444D40361070B4F86082D4B2AAC
7177C68A836B94054304F0D00363070B
4C86082C4B4BAC6677CA8A706B910537
04F9CE035F070B5686082C4B2DAC6877
C98A546B9205370497D0035B070B6486
082C4B29AC5377CF8A416B63053C0465
D40361070B7386082C4BEFAB5777DB8A
356B5F05430493D2035F070B7F86082D
4B6CAB6277D98A276B66053B0425D703
5F070B8E86082D4B3CAB7777DD8A126B
62053904F3E20363070B8C86082C4BA2
AA6C77D38A1A6B3E054104B7ED036807
0B3A86082C4BCCA92C77D08A3B6B4005
410482ED0361070B5A85082C4B82A963
76D78A2A6B3D05420432E40363070B44
84082C4BA4A9C475E38A166B42054204
C1DB0361070BB683082C4BC4A98275E4
8A266B31053104B2D80363070BB08308
2C4BD7A99875D98A2A6B290526048ED7
0363070BE583082B4BB9A9B975C28A17
6B310530047BD40363070B0784082B4B
C0A97075B68A0E6B320533046BD10366
070B0284082B4BCFA93275AB8A036B50
053E04E2CC0368070BF683082B4B26AA
1875B98AFA6A4B053E0455C90369070B
FC83082C4B4EAAFF74C68AF76A50053C
04EDC6036A070B1584082B4B29AAFE74
D48AE66A4F053B04CEC3036A070B2484
082B4B16AAF474C88AD26A5505430454
C0036A070B0084082A4BDAA98074B98A
E46A5A053E0498BD0368070B5A83082B
4BB3A9BF73DE8AE06A6205420475BD03
66070B2982082C4B46A9FC72F78ADB6A
61053E04E3BF0369070B2781082C4B81
A8A472FD8AE86A670540041AC2036607
0B0681082C4BDDA7C372CA8AF16A3805
3D0495C40366070B5D81082B4B56A709
73B88A1C6B35054404F3C60368070BAE
81082B4BE6A6E172CD8A006B3C054204
99C70366070BDA81082C4BA4A6CF72DB
8A156B45053F0414C60366070BDE8108
2C4BB7A6B672F08A0C6B5E05490486C5
0369070B0282082C4B11A7EB72FD8A1B
6B5F054A0451C5036A070B5082082C4B
4AA72173048B096B5C05540407C2036A
070B9682082C4B70A72573FD8A046B61
05590404BD0368070BBB82082C4BAFA7
1D73E68AEF6A9F05510491B80368070B
C082082C4B06A8FB72BD8AF86A98054E
0474B50369070B9782082C4B32A8B372
688A196BA1054E04F9B30368070BFA81
082C4B25A83D72AE8A096B9C054F04CC
B30368070BC480082C4B1DA88B71FB8A
0A6B8E0541042EB50368070B767F082C
4B14A8A471378B2F6B970546046FB703
6A070BE17E082B4BDCA70372418B3C6B
87053904BBB80368070BE07E082C4B94
A72E72288B346B92054404E4B8036E07
0B057F082C4B78A775721D8B1C6B8D05
400412B7036C070BFD7E082D4B70A7A8
72FD8A246B5005400441B4036C070B9F
7E082C4B81A74E720D8B356B4F054104
9CB3036A070B2B7E082C4BC0A7087236
8B6F6B4F053C04D9B4036A070B107E08
2C4B0DA80D725A8B5E6B4B053E048FB5
036C070B3E7E082D4B72A83271608B58
6B5205420427B5036E070B797E082D4B
D6A8BC712F8B536B54054104A0B30372
070B8F7E082D4B2DA9B172EA8A5A6B50
053A0480B00370070B467E082D4B77A9
19740A8B716B4A053A0448AE0370070B
AC7D082D4BB7A90A74508B566B5E0555
048FAD036E070B287D082D4B12AAA273
648B506B630553049FAD0372070BD67C
082E4B63AA70725C8B596B61054D0416
AD0376070B817C082E4BF8AAB875918B
5F6B5E05530410AC0377070BD67B082D
4BA8AB477BAA8B796B2D053904C2AA03
77070BA77A082E4B45ACA681C78B066B
34053C04E7A90379070B3779082D4BC8
AC5F8AD18B756B3105400415A9037D07
0BA977082D4B5BAD1B8DEF8B5C663105
3B04D0A7037F070BB676082D4B0BAE5F
8F078CBA669E04CE03CDA40384070BE5
75082D4B9EAE83B9BE8B9C669B04D003
ADA0038C070BDD74082D4B43AF11B9A6
8B1A66AA04D2033E990388070B657408
2D4BC1AFDAB8A48BEC6A9F04D5032895
037F070B5F74082C4B63B00DB9898B12
66A004CA039798037B070BBC74082C4B
C3B04B9A9F8B3766AF019E00E99B037D
070BE774082C4BA8B0EAB87E8B4C66B3
019B004F9D0380070B8C74082C4BE1AF
D7B7758B2366B0019E00A79D0381070B
C573082C4BA3AE4398818B3866B6019B
00899D0381070B8F73082B4B17AD1BB7
B48B47667A0054052B9D037F070BAC73
082B4B83ABA9B6BA8B87667E005905D3
9C0383070B9A73082A4B0DAA18B7718B
786A85005B05A79C0388070BD573082B
4B90A830B79C8B5A6680005305A19B03
89070B9D73082B4BF9A64AB7C38BD765
29036B03B799038E070B3173082B4B25
A67BB7A58B036822036D030998033705
0B2D73082B4B72A675B7788B576E2503
6E03E3960369030B2E73082B4B86A7D0
B67F8B6F6C24037003A596035E030B2F
73082B4B78A8CAB59F8BCD68B0027D03
F696035E030B2E73082A4B88A92AB59A
8B8C67AF0277037B97035C030B2D7308
2A4B56AA2CB4818B9367B70281030598
034F030B2E73082A4B9EAAD3B3808B0A
67B4027C03</Data>

   <DataCRC>1078a62a</DataCRC>

   <BytesSent>14421</BytesSent>

</SBEDataUpload>
</InstrumentRawData>
</SBEDataUploadFile>
