<?xml version="1.0"?>
<!-- SCPlusV2_RS232 -->
<SBEDataUploadFile>
<ApplicationData>
<Seaterm232>
<SoftwareVersion>2.8.0.119</SoftwareVersion>
<BuildDate>07-Nov-2018</BuildDate>
</Seaterm232>
</ApplicationData>
<InstrumentState>
<HardwareData DeviceType='SBE19plus' SerialNumber='01907809'>

   <Manufacturer>Sea-Bird Electronics, Inc.</Manufacturer>

   <FirmwareVersion>3.1.8</FirmwareVersion>

   <FirmwareDate>Mar  9 2016 16:22:29</FirmwareDate>

   <CommandSetVersion>1.4</CommandSetVersion>

   <PCBAssembly PCBSerialNum='120721' AssemblyNum='41054J'/>

   <PCBAssembly PCBSerialNum='120715' AssemblyNum='41967A'/>

   <PCBAssembly PCBSerialNum='116699' AssemblyNum='41606'/>

   <PCBAssembly PCBSerialNum='120719' AssemblyNum='41059D'/>

   <MfgDate>28-Apr-2017</MfgDate>

   <InternalSensors>

      <Sensor id='Main Temperature'>

         <type>temperature0</type>

         <SerialNumber>01907809</SerialNumber>

      </Sensor>

      <Sensor id='Main Conductivity'>

         <type>conductivity-0</type>

         <SerialNumber>01907809</SerialNumber>

      </Sensor>

      <Sensor id='Main Pressure'>

         <type>strain-0</type>

         <SerialNumber>10586018</SerialNumber>

      </Sensor>

   </InternalSensors>

   <ExternalSensors>

      <Sensor id='volt 0'>

         <type>pH</type>

         <SerialNumber>27-0363</SerialNumber>

      </Sensor>

      <Sensor id='volt 1'>

         <type>ORP</type>

         <SerialNumber>27-0363</SerialNumber>

      </Sensor>

      <Sensor id='volt 2'>

         <type>OXY</type>

         <SerialNumber>43-0434</SerialNumber>

      </Sensor>

      <Sensor id='volt 3'>

         <type>PAR</type>

         <SerialNumber>1122</SerialNumber>

      </Sensor>

      <Sensor id='volt 4'>

         <type>ECO AFL/FL</type>

         <SerialNumber>FLNTURT-2496</SerialNumber>

      </Sensor>

      <Sensor id='volt 5'>

         <type>ECO-NTU</type>

         <SerialNumber>FLNTURT-2496</SerialNumber>

      </Sensor>

      <Sensor id='serial'>

         <type>not assigned</type>

         <SerialNumber>not assigned</SerialNumber>

      </Sensor>

   </ExternalSensors>

</HardwareData>
<StatusData DeviceType='SBE19plus' SerialNumber='01907809'>

   <DateTime>2019-07-12T12:59:51</DateTime>

   <LoggingState>not logging</LoggingState>

   <EventSummary numEvents='0'/>

   <Power>

      <vMain>12.8</vMain>

      <vLith>8.6</vLith>

      <iMain>63.0</iMain>

      <iPump>123.3</iPump>

      <iExt01>19.1</iExt01>

      <iExt2345>36.6</iExt2345>

   </Power>

   <MemorySummary>

      <Bytes>253115</Bytes>

      <Samples>11005</Samples>

      <SamplesFree>2849783</SamplesFree>

      <SampleLength>23</SampleLength>

      <Profiles>10</Profiles>

   </MemorySummary>

</StatusData>
<ConfigurationData DeviceType='SBE19plus' SerialNumber='01907809'>

   <ProfileMode>

      <ScansToAverage>1</ScansToAverage>

      <MinimumCondFreq>5</MinimumCondFreq>

      <PumpDelay>45</PumpDelay>

      <AutoRun>no</AutoRun>

      <IgnoreSwitch>no</IgnoreSwitch>

   </ProfileMode>

   <Battery>

      <Type>alkaline</Type>

      <CutOff>7.5</CutOff>

   </Battery>

   <DataChannels>

      <ExtVolt0>yes</ExtVolt0>

      <ExtVolt1>yes</ExtVolt1>

      <ExtVolt2>yes</ExtVolt2>

      <ExtVolt3>yes</ExtVolt3>

      <ExtVolt4>yes</ExtVolt4>

      <ExtVolt5>yes</ExtVolt5>

      <SBE38>no</SBE38>

      <WETLABS>no</WETLABS>

      <OPTODE>no</OPTODE>

      <SBE63>no</SBE63>

      <SeaFET>no</SeaFET>

      <GTD>no</GTD>

   </DataChannels>

   <EchoCharacters>yes</EchoCharacters>

   <OutputExecutedTag>yes</OutputExecutedTag>

   <OutputFormat>raw HEX</OutputFormat>

</ConfigurationData>
<CalibrationCoefficients DeviceType='SBE19plus' SerialNumber='01907809'>

   <Calibration format='TEMP1' id='Main Temperature'>

      <SerialNum>01907809</SerialNum>

      <CalDate>24-Mar-19</CalDate>

      <TA0>1.217923e-03</TA0>

      <TA1>2.816693e-04</TA1>

      <TA2>-1.603333e-06</TA2>

      <TA3>1.984146e-07</TA3>

      <TOFFSET>0.000000e+00</TOFFSET>

   </Calibration>

   <Calibration format='WBCOND0' id='Main Conductivity'>

      <SerialNum>01907809</SerialNum>

      <CalDate>24-Mar-19</CalDate>

      <G>-1.005893e+00</G>

      <H>1.268163e-01</H>

      <I>-1.515604e-04</I>

      <J>2.671373e-05</J>

      <CPCOR>-9.570000e-08</CPCOR>

      <CTCOR>3.250000e-06</CTCOR>

      <CSLOPE>1.000000e+00</CSLOPE>

   </Calibration>

   <Calibration format='STRAIN0' id='Main Pressure'>

      <SerialNum>10586018</SerialNum>

      <CalDate>11-Mar-19</CalDate>

      <PA0>4.565618e-02</PA0>

      <PA1>4.850951e-04</PA1>

      <PA2>-2.883271e-12</PA2>

      <PTCA0>5.252467e+05</PTCA0>

      <PTCA1>1.223042e+01</PTCA1>

      <PTCA2>-3.567450e-01</PTCA2>

      <PTCB0>2.516687e+01</PTCB0>

      <PTCB1>3.750000e-04</PTCB1>

      <PTCB2>0.000000e+00</PTCB2>

      <PTEMPA0>-5.487846e+01</PTEMPA0>

      <PTEMPA1>5.537568e+01</PTEMPA1>

      <PTEMPA2>-5.867271e-01</PTEMPA2>

      <POFFSET>7.140000e-01</POFFSET>

      <PRANGE>1.600000e+02</PRANGE>

   </Calibration>

   <Calibration format='VOLT0' id='Volt 0'>

      <OFFSET>-4.920000e-02</OFFSET>

      <SLOPE>1.248122e+00</SLOPE>

   </Calibration>

   <Calibration format='VOLT0' id='Volt 1'>

      <OFFSET>-4.784000e-02</OFFSET>

      <SLOPE>1.248871e+00</SLOPE>

   </Calibration>

   <Calibration format='VOLT0' id='Volt 2'>

      <OFFSET>-4.864632e-02</OFFSET>

      <SLOPE>1.248714e+00</SLOPE>

   </Calibration>

   <Calibration format='VOLT0' id='Volt 3'>

      <OFFSET>-4.743790e-02</OFFSET>

      <SLOPE>1.248571e+00</SLOPE>

   </Calibration>

   <Calibration format='VOLT0' id='Volt 4'>

      <OFFSET>-4.671263e-02</OFFSET>

      <SLOPE>1.248951e+00</SLOPE>

   </Calibration>

   <Calibration format='VOLT0' id='Volt 5'>

      <OFFSET>-4.871053e-02</OFFSET>

      <SLOPE>1.249136e+00</SLOPE>

   </Calibration>

   <Calibration format='FREQ0' id='external frequency channel'>

      <EXTFREQSF>1.000014e+00</EXTFREQSF>

   </Calibration>

</CalibrationCoefficients>
<EventCounters DeviceType='SBE19plus' SerialNumber='01907809'>

   <EventSummary numEvents='0'/>

</EventCounters></InstrumentState>
<Headers>

cast   2 10 Jul 2019 21:15:55 samples 1328 to 2220, avg = 1, stop = mag switch

</Headers><InstrumentRawData>
<SBEDataUpload startAddr='30521'>

   <Type>1</Type>

   <DataFormat>SEACATPLUS0</DataFormat>

   <Bytes>20539</Bytes>

   <Data>
50A503D2020B687208AE4964996406A0
77134CE302890352A503CE020B667208
AE4964996606AA77754DE0028C0353A5
03D0020B667208AE4958996406A67747
4EDB02910359A503CE020B677208AE49
639967069F779C4EE202960359A503D0
020B667208AF49629962069777174FDA
028D035CA503CE020B657208AF496899
66069B77E54FDF028B035BA503D0020B
647208AF496D99600698775750E60298
035DA503D0020B677208AE4958996206
A077B750E6028D0360A503D0020B6572
08AE495D9968069C771D51DA02A50360
A503D2020B657208AF496B995F069777
7C51E002A10361A503D4020B667208AF
49649968069D77E651E8029F0361A503
D2020B657208AF49649966069D773152
E002990364A503D4020B667208AF4965
9963069777A252E602A10367A503D202
0B657208AF495C9963069477D452DF02
9A0366A503D2020B657208AF496D9964
0697771D53DC02A10369A503D2020B64
7208AF496A995F06A1773A53E1029F03
6BA503D2020B637208AF495999660696
776953DD0290036AA503D2020B657208
AF4962995E0687774254E10292036CA5
03D2020B647208B049619964068E7729
53E30293036FA503D0020B647208B049
6F99650693772253DD0297036EA503D2
020B657208AF49639966068E772953E1
028D0371A503D4020B657208B0496499
6A0691770853E5028D0375A503D2020B
657208B049609969069077E452E1028D
0376A503D2020B657208B1495E996406
8D779C52DB02920378A503D2020B6472
08B1495C99650686776A52E102940378
A503D2020B647208B149619965069577
4E52E50295037AA503D2020B647208B1
495E99640692772C52DF0292037BA503
D2020B647208B2495E9962069577D151
E1028C037DA503D0020B657208B24961
9968068D778951DF028B0380A503D002
0B647208B1495D995F0697776751E602
8B037FA503D0020B647208B2495C9966
069C774751E002900382A503D0020B63
7208B24964996A0696773A51E1028E03
83A503D2020B637208B3495E99640696
773A51E102960385A503D0020B637208
B3495C9968069C773051E302940388A5
03D2020B657208B349629963069C7734
51DF02890387A503D2020B647208B349
5C99650697773651DF028D0387A503D0
020B627208B3495E99630696772F51E1
0296038BA503D2020B637208B3496099
6B069D772551D90291038DA503D2020B
637208B349609963069A773151D2028E
038FA503D0020B647208B4495A996806
A1773351D302930391A503D0020B6372
08B44960996106A3772F51DC02920393
A503D0020B637208B4495A996506A077
5051E102910393A503D0020B637208B3
495A9966069F774B51DB028E0395A503
D4020B637208B4495A9965069C77EC50
DF028A0399A503D0020B647208B44961
996F0686775A50E40291039AA503D002
0B657208B449679961067A77EE4FDB02
90039AA503D0020B647208B449649964
0684778D4FD00296039CA503D2020B64
7208B449619964069D77494FCC029003
9EA503D0020B667208B4496299610698
77D14ECC0290039DA503D4020B647208
B449659964069677934ED2029503A3A5
03D4020B637208B4495C996B069C7779
4ECF028E03A5A503D6020B647208B549
64996806AC77FB4DD3029403A6A503D6
020B657208B54962996206A177144ECC
029603A5A503D8020B657208B5495C99
63069C77324ED4029203A6A503D4020B
647208B54962996206A3773F4ED3028B
03A8A503D8020B647208B54958996D06
A477474ED2028F03AAA503D8020B6472
08B64962996006A177324ECC029203A9
A503DB020B647208B54962996406A277
334ED3029203ACA503DD020B647208B6
4969996806A377144ECC028903ACA503
DF020B647208B6496D996006A577134E
D0029803AEA503EB020B627208B64969
996506AF77504ED7029003B0A503EE02
0B667208B64963996606B377614FD402
9103B0A503F2020B677208B549649966
06BE777952D602980321A50316030BEE
7208B649669966066078F562D7029703
EC8F0305030B2D7308B5496F996606EC
790465CE028B038E6A03F6020B367308
B5495E9967062D7B5766CE028D036A52
03F6020B357308B5495E996A061F7CAB
67D1029003964503F0020B2A7308B549
67996506B87C0569DB028E03973E0301
030B4A7308B549669962067D7D6F69CA
028B03FE3A0389040BA47308B4496499
6206A67F826ECC029A034A380358060B
317408B54960992509E5826E6FD80290
033E350398060BE77408B5495E996406
8484146DE202A103C732039E060BB875
08B4494B9962061C86686EE102A1039B
3003A2060B617608B5495C9968066086
F26EDC02A003C42C03A2060BEC7608B5
4964995F06C986866EE402A303B82803
A2060B667708B449A4996506F086206E
AD03040D8025039E060BB77708B54905
9A6606AC86C46DAA03FA0C4C23039A06
0BF17708B549639A66064686D86DA503
F90CC8210398060B487808B549CD9A63
06D985EE6DAF03FC0C05210395060BB7
7808B5492A9B68065985EC6DA003E103
AF200395060BEF7808B549849B66068E
84BF6D9803DF035C200393060BF27808
B449E09B64061284866D9C03DF036620
0393060BEF7808B549229C6306AE835C
6DA003DB03CE200395060BDF7808B549
649C6C0634833A6D9903E4034C21039C
060BBF7808B549889C6006B382186D9E
03DE03B521039C060BB07808B549809C
65062C82F46C9C03DD034522039E060B
A77808B4499C9C6606B181DE6C9E03DF
037A2203A0060B9E7808B449F29C6206
3781BB6C9C03DB037F2203A2060BB478
08B449A29E6206BB80B36CB103DE0381
2203A0060BC97808B4499E9E66060D80
A66CAF03E303352203A2060BCD7808B3
493E9D6406407F956CAB03E103B12103
A2060BC97808B449E79A64069C7E816C
A703DB03272103A0060BCE7808B34990
986006337E696CB103E303DC2003A206
0BEB7808B349A7966406F57D506CA903
E003E42003A4060B177908B349C89460
06A07D4A6CAE03DD03E82003A0060B1C
7908B3496B935D06107D296CA903DF03
CF2003A0060B0E7908B34939926506A4
7C276CC103EA038020039E060B077908
B4492791320D4B7C116CBA03E0032720
039E060BFB7808B549D68F450EE37BF2
6BB603E103DA1F039E060BF67808B549
9D8ECF0BB07BE16BB703DF039E1F03A2
060BFB7808B449668D0F078A7BC96BC0
03DE03A81F03A0060BFB7808B549448C
6806697BB16BC403E603EF1F03A0060B
F87808B549378B6106427BA06BBC03E4
03262003A2060BFC7808B549F9896006
0D7B976BBA03E603412003A2060B0679
08B5498E886906E27A776BBF03DE0365
2003A0060B077908B5492F876406BC7A
7C6BC003DD03802003A0060B097908B6
49D6856106977A616BBC03E0036D2003
A0060B107908B649AD846306787A466B
B303DD03662003A2060B117908B649E2
836406557A3E6BBD03DF038B2003A006
0B097908B5497B836A062D7A346BBC03
DF03C12003A2060B027908B649928362
06127A246BB903E003CC2003A4060BFE
7808B7492D846006EE79126BBB03E603
E02003A2060BFA7808B64905856806D6
79086BBE03E103F92003A2060BFC7808
B649E6856606C079FA6ABD03DF030821
03A2060BFB7808B5499C866206A179E4
6ABC03E703182103A0060BFA7808B549
5A8762067E79D26ABC03DE032B2103A0
060BF77808B549DF8766067379D26ABC
03DB032C2103A0060BFB7808B4498C88
6A065D79C06AAD03DF032D2103A2060B
FF7808B449F48863064679B96AB103E2
03372103A0060B037908B44929896406
3679A46AAA03DF033A2103A2060B0479
08B4494D896C062B79966AAA03DF033B
2103A0060B067908B4496D8966061479
7F6ACC03E303472103A0060B057908B3
4995896206FF78756ACE03E503602103
9E060B037908B349A0896106EE78706A
CD03E003692103A2060B077908B4498F
896806DD78646ACD03E1035C2103A006
0B087908B44987896506CE78506ACA03
DE035D2103A0060B0A7908B3495C8964
06C178516AC003E303602103A2060B1E
7908B34932895F06B1784F6ABE03E603
5B2103A2060B3E7908B34906896B066C
78466ABF03DF03A52103A0060B4D7908
B349EA885C06BE77366ABA03DE032622
03A0060B527908B349E8886006E8762E
6ABA03E103562203A2060B647908B449
C6886A068576276AC003DC031522039E
060B927908B54979886B068376186ABC
03DF0319220395060B8F7908B5494788
6D06FE75266ABF03DF0349220395060B
3A7908B449DC8764060676326AAF03DF
036022039A060B0F7908B44960876506
33761A6AB103E403FD22039A060B1579
08B449B48667063A76096AB103E40324
23039A060B097908B4494D8667061176
066AAF03DE03BD220394060BF67808B5
49F1856806F275036AD003DF031A2203
93060BF17808B54944856206EB75F869
CC03D90396220393060B107908B44968
8460061B76F369CB03DD038324039106
0B1E7908B5494E8360062676E469CB03
EA032926038F060BE97808B54944825D
06FE75E769C903DD03FA260391060BAF
7808B6492A8168061176E469CF03DD03
96270394060BC27808B649FE7F660616
76DC69CF03DB0386270393060BE97808
B7497B7F5C06E775CC69CE03E1035727
0391060BF77808B7498F7F63069175AF
69CD03E503F826038D060BF17808B649
8C7F60063075AF69BC03DD030427038F
060BEB7808B649677F60060C75A969C5
03E4033B29038F060BE97808B549107F
67060375AD69C303E0032D2B038F060B
E77808B6496B7E5F061A759E69BB03DC
03B32B0392060BEE7808B649C27D5D06
3A758C69CD03DA03B72B038F060BF178
08B749727D680655757C69C803DD03EA
2B038D060BEE7808B7495E7D5F066B75
7B69C903DE034D2C038D060BF07808B6
495B7D660684756F69CA03E303AD2C03
8D060BF87808B6493B7D620696756C69
CA03E103EC2C038D060BFC7808B54912
7D620699755569CC03E303132D038B06
0BFA7808B549C47C640695755B69CD03
E2032F2D038E060BFF7808B549607C64
0698755169C803E803302D038B060B07
7908B549097C66069A753C69BE03DD03
242D038D060B107908B549B87B630699
753E69B403DE03312D038D060B287908
B4495A7B62069D753C69B903DB03422D
038F060B557908B449EE7A6806AC7547
69BF03E703522D038D060B9E7908B449
857A60068A756169C003D703512D038A
060BEC7908B549FA795B0609756C69C3
03E1035E2D038B060B307A08B5499479
69068D746E69BC03E1037A2D038D060B
747A08B5490679670629747069C003E1
039D2D038B060BC27A08B5495F785F06
0A746C69C003DD03B52D038D060B1A7B
08B549C67768060A746C69B003DF03B7
2D0389060B637B08B549277769063174
6869AB03E003C12D038B060BB27B08B6
499E766A0611745669B003E103D52D03
8A060BFF7B08B649F475640618745369
B403E203F42D038D060B3D7C08B6496B
75680647745269B103F403EA2D039106
0B8A7C08B6494E7568068C744669A903
EB03F62C0395060BFC7C08B5492E766A
06B8742869B103F1033B2B0397060B75
7D08B549D6776606AC741069B503F103
F429038B060BB97D08B549BF79660673
740069CA03EB038C28038B060BD87D08
B5491C7B6A064B74F468C603F0031527
0390060B207E08B549F97B5E064274EA
68C703F003AA26038F060B6A7E08B549
437C5F061374DB68CF03F0032D26038D
060B7E7E08B4494E7C64061574D568C2
03F203702503A0060B8C7E08B449147C
62061474CA68BB03F003FF2403A8060B
927E08B349317C5E061174B868B603F0
03C02203AB060BB07E08B349FF7E6806
2C74AD68BC03ED03952003AB060BDE7E
08B349958462065774A168C203EA0328
1F03AB060BEE7E08B349858A68066B74
9D68C003F003531E03AB060BE87E08B3
49F08E64066774A368BE03EB03D51D03
AD060B157F08B3495F92700676749568
C303EB038A1D03AB060B5C7F08B349B1
9464063F748D68B903F003651D03AD06
0B687F08B34974965D06E8737D68A903
F403501D03AB060B507F08B449AD9762
06D9737668A303EC03421D03AB060B47
7F08B4497D986606F2736D68A903EC03
331D03A8060B497F08B449E69860060B
746968AA03F0032F1D03AB060B4A7F08
B4491D99680611745C68AD03F203311D
03AB060B507F08B54944996906117459
68A503EF03371D03AB060B537F08B449
68996106F4735368AD03EC033B1D03AB
060B4C7F08B449A399610601744B68AB
03EF03381D03AB060B517F08B449D099
690618744568BD03F703411D03AB060B
597F08B549E499640626743868C003F1
03401D03AB060B537F08B549FA996406
2B743968BC03E603411D03AB060B477F
08B549119A600622743668B403F6034D
1D03AD060B467F08B549329A60061374
2B68B203E103741D03AD060B537F08B5
494D9A630604742968AD03E8038C1D03
AD060B917F08B549759A6306FC732368
AC03DB03821D03AD060B168008B5497D
9A5F06C6731C68A703DE03691D03AB06
0B7F8008B5499B9A620699732268B903
EE03571D03AB060BE28008B449B19A63
0685731668BC03F503471D03AB060B34
8108B449C59A6A0682731068C503ED03
3C1D03AB060B548108B449D09A63067C
730D68B703F203401D03AB060B738108
B449CD9A6A067C730168BA03EF03471D
03AB060B8F8108B449CA9A6006817300
68B903F103511D03AB060BA48108B549
C79A66069973FD67BE03ED03541D03AB
060BEF8108B549B09A6206AB73F567BD
03EB03531D03AD060B4B8208B549899A
6806B473FA67BA03EC03531D03AD060B
8D8208B549759A64069F73EB67B203F5
03561D03AB060BB18208B4497C9A6306
9B73EF67AD03F603571D03AB060BD582
08B449AB9A5C069C73E067A703F1035A
1D03AB060BEE8208B449D69A64069873
E967AC03EC035B1D03AB060B098308B4
49F29A67068A73D667BB03E703611D03
AB060B398308B449DD9A63068173CA67
C403F003621D03AB060B4F8308B449D7
9A62065673C267BA03F203661D03AB06
0B5A8308B449CC9A64064773BD67BA03
F703701D03AD060B718308B549BF9A69
064D73BA67DB03DF03751D03AB060B94
8308B549C59A68066B73BA67E503DB03
811D03AB060BC48308B649E89A68068E
73A967E303E6038A1D03AB060BF48308
B7490A9B67069173A867E303E2038F1D
03AB060B2A8408B749039B6A06A173AA
67C903EE039A1D03AB060B7F8408B649
059B680698739C67CB03EE03A61D03AB
060BD08408B649F29A65068473A467CA
03F303AB1D03AB060B128508B649EE9A
66067F739D67CF03ED03B61D03A8060B
5B8508B649FB9A620669739267C903F2
03CA1D03AB060B9C8508B6491D9B6206
45738A67CF03F103EA1D03AD060BC285
08B649289B6A0637738A67CB03F0030E
1E03AB060BDC8508B549119B6B063373
8367D303F403251E03AD060BF78508B5
49089B650643737367CD03F003321E03
AB060B178608B649F99A620667737567
C903F303391E03AB060B378608B649D5
9A640678736D67CF03EF033B1E03AD06
0B588608B649D09A66068F736B67D003
F1033F1E03AB060B6B8608B549CD9A63
0692736A67CF03F403431E03AB060B78
8608B549D69A660697735F67DB03EE03
451E03AB060B818608B449D69A660694
735F67E103F403431E03AD060B928608
B449CF9A660685735967E103EC03401E
03AB060BB08608B449BF9A660695735C
67E303F103411E03AD060BDD8608B449
B29A6506B9735467DA03EE034C1E03AD
060B038708B449B09A6806D0735067E1
03EB03601E03AB060B1A8708B449DB9A
5D06C8734067DD03F303681E03AB060B
2D8708B449DD9A6006CB734667E003EB
03611E03AB060B528708B449C79A6306
E1733D67D803F0035D1E03AB060B7E87
08B549AF9A6506DF734167E303F00363
1E03AB060BB58708B549AF9A5F06E873
3B67E403F803751E03AD060BED8708B6
49B09A6C06CA732E67E403F003901E03
AD060B138808B549B49A6106A8732867
D803E903A51E03AD060B348808B549A7
9A6006A4732B67CB03F003B71E03AD06
0B688808B649B39A6206AC732A67C903
F003DA1E03AD060BBD8808B649C29A62
069C732867D203F203211F03AB060B09
8908B749C79A64066C731E67CB03F503
8A1F03AB060B3F8908B649B29A6A064C
732867E103F203F21F03AB060BB98908
B649839A630656731E67DD03F1033F20
03AB060B238A08B649659A6006657319
67DA03EA039D2003A8060B3C8A08B649
4C9A5D0645731267E103F003FB2003AB
060B418A08B6492B9A67064E731D67C8
03EA031D2103AB060B5D8A08B649F699
660678731967C903F2031D2103A8060B
7F8A08B649E199630692730C67D303F2
03362103A8060B888A08B649E2996606
84730567CF03F2034F2103AB060B8B8A
08B549FF9963068273FF66CF03F6034E
2103AB060B9A8A08B549259A64069B73
0167CB03F7032D2103AB060BBC8A08B5
49309A6A06B973F466C803EE032F2103
AB060BC88A08B549219A6306C673FB66
D103EE03472103A8060BC68A08B5490F
9A6706EA73FE66C903EE03452103AB06
0BC78A08B449FC9966060274E766C203
F703352103A9060BC78A08B449EB9967
061274F166CB03F2032D2103AB060BD1
8A08B449D69967062674E566CD03ED03
362103AB060BDE8A08B449D69965062E
74E366CA03EE03362103AB060B098B08
B449CB9961064074E666DA03EE033921
03A8060B4B8B08B449F1996A063E74DF
66D603F103652103A8060B6C8B08B349
F4996F06FC73DD66DE03EC039B2103A8
060B8B8B08B349EE996506EA73DE66DB
03F403B92103A9060BBE8B08B449ED99
6406D773D866BC03EF03EB2103AB060B
D08B08B449039A6206CD73DE66BF03EE
031B2203A8060BF18B08B349F1996806
DD73D866B703F0032D2203AB060B408C
08B449FE996006F173C966BE03F10325
2203AB060B7F8C08B349FF996406E473
CF66CD03ED03212203AB060BAB8C08B3
49F9996A06DE73CA66CD03EB03112203
AB060BD88C08B349E0996806CE73C166
C303ED030C2203AB060BFC8C08B349CF
996806B873C966CB03F003152203AB06
0B248D08B349C9996206AE73BD66F403
0104252203AB060B408D08B349BD995E
069973BD66E903FE03362203AB060B63
8D08B349B29966069F73B466EE03FF03
3E2203A8060B848D08B349A5996406AD
73A966EB03FD03502203AB060B938D08
B349939966069C73A966BC03F0036F22
03A9060BB98D08B34972995D06A873B0
66BC03F1038E2203AB060BF98D08B449
47995F06AE73AD66C403F303C92203A8
060B3B8E08B44907996606BB73A966B6
03EE03142303AD060B7B8E08B449D098
6306B7739466B503EC035B2303AB060B
988E08B449AC9863066E73A166D103FF
03922303AB060B8F8E08B5498D986006
4D739966C7030104A62303AD060B9F8E
08B5494A98630670739C66C703010499
2303AD060BBD8E08B549019863067D73
9666CB03FB03AA2303AB060BC98E08B4
49D297670679739666CD03F603AD2303
AD060BF18E08B449BA976606A8739A66
D403F103B52303AD060B378F08B449A7
976506C1739566C903F303D02303AB06
0B6D8F08B549B6976A06DB739166CA03
EE03062403AD060B888F08B549CF9762
06D3738066CD03F0032A2403AF060B9B
8F08B549D6975D06D0738166CC03F103
422403AB060BC28F08B549D8976A06DF
738266D003EF03492403AD060BFA8F08
B449B8976806F1738066CD03EE033024
03AB060B309008B449AE976C06FD737A
66EF03EE03202403AB060B699008B449
8A97640600747366F003FA03202403AB
060BA89008B4496797620601746F66EE
03EC035C2403AB060BE19008B4496A97
6206FB736866E903EA03CA2403AD060B
209108B4495B975F06D5735A66CB0302
04102503A8060B409108B44944976406
72736266CD03FE033D2503AB060B4A91
08B3495897670658735B66CD03060456
2503A8060B559108B449589765064673
5C66CF03FD03612503AB060B639108B4
497B97660656735266CB030404632503
AB060B949108B449BA9760067C735166
CB03F103772503AB060BBE9108B549E8
97640699734B66C903F103942503AB06
0BE69108B549EF976606AC734E66CD03
EF03AC2503AF060B269208B449E19768
06A3734066C903E903C92503AD060B49
9208B449D397610674734B66CF03F003
F02503AD060B699208B449A89761068A
733E66C703F0030A2603AD060B9A9208
B4498597680699733C66D103EE031C26
03AD060BD79208B4492F976806D37347
66CB03EB03362603AD060B399308B449
F8966806FD733766C9030304882603AF
060B8F9308B349CC9669060A742D66CF
03FF03DB2603AD060BBF9308B349B196
670608743566CE0301041F2703B1060B
DD9308B3497996660619742366CA0300
044D2703AD060BF89308B34925966406
1F741C66DC030104722703AD060B1194
08B349E89561061B742266DD0308049A
2703B1060B449408B349B29567062974
2266E1030204FF2703AD060B809408B2
4970956C062D742266DA030604E12803
A8060BB69408B1493A95680633740E66
BD030D04D52903A8060BE49408B14915
9563063D741066B8031104572A03AD06
0B009508B249F594650639740B66C303
1404782A03AB060B169508B249E79460
0638740266C4031004A42A03AD060B31
9508B249129566063E74FD65BC030F04
BB2A03AB060B609508B34927955D0646
740066B903F903C42A03A6060B9E9508
B249309565065174FF65C003FF03EC2A
03A6060BEF9508B3492B9562064174F8
65BE03FF03132B03A2060B539608B349
279560063574EB65B903FA03A22B03A2
060BAF9608B2494A9560063074F265AD
03FD03422C03AB060BFC9608B2498395
60062474EA65AF030104342D03B1060B
459708B349D19567063174E665AF0306
04EF2E03B5060B7A9708B34944966306
2C74DF65AB030904F03003B5060B9097
08B3498D9665061374E665BE03FF03AB
3203B3060BA69708B349639664060874
DE65B903FA03053403B7060BCE9708B3
49B79560061974DC65BD030004B73503
B9060BF79708B449D69461062674DF65
BD030504543703B9060B2A9808B349E7
9365063874DA65BB030104883803B906
0B5F9808B44909936B063F74D065BB03
FD03CF3903BF060B919808B349239266
063D74D165C30305043C3B03BE060BE3
9808B349709166063B74CD65C2030204
BD3C03BE060B319908B249E3905D062F
74CA65C203FF03543E03C0060B6A9908
B3492D9068061574C065BA03F803C03F
03BC060B9F9908B349768F6A061874C0
65BE030204F64003B7060BE69908B449
CA8E6C061174B765BE0301045E4203B5
060B289A08B5491E8E68060374AE65B6
03FE03844403B3060B679A08B449888D
62060674A565C203FF03AD4603B3060B
AB9A08B449088D5B06EB739565B70302
04184803B3060BE09A08B349FF8C5D06
D5738A65C003FF03864803B1060B249B
08B349568D5A06D5738365C003040494
4803AD060B7B9B08B349F08D6406CC73
8265D903FF03534A03A8060BCB9B08B4
49908E6406DB737B65DE0300049F4F03
A6060B189C08B449E68E6406E8737965
DF0302046456039E060B6C9C08B4490E
8F6A06F5737065E0030104465E039C06
0BBE9C08B3492C8F5F061A746865E003
010451670395060BF99C08B449248F62
061B746265DE03FF039E700393060B1A
9D08B449CF8E610620745765E1030404
58780393060B299D08B549438E5F061C
745D65DC03FF03957B0396060B429D08
B449888D61062B745565F2030E04ED7C
0395060B5B9D08B449FE8C68063E7454
65EF0312048A7E0393060B749D08B449
5F8C630646745065E3030E04FA7F0393
060B9C9D08B349E58B6A0656744665EB
0310046C7F0393060BD09D08B349738B
600660744365FD031504DC7B0393060B
0E9E08B449248B6A0664743865FF030E
042A7A0393060B419E08B449C68A6006
55743F65FB031204547B0394060B679E
08B4497F8A61065A743265FE031004F1
7B038F060B959E08B449438A60065D74
3065FC031004977B038D060BC39E08B3
49338A650666742565F6030704F77D03
86060B019F08B349068A610660742B65
FC031104C6850386060B459F08B349BB
8968065A742665FC031304F58E038406
0B779F08B3494789680647741F65FE03
13044B960382060B979F08B349C08863
06477415650F040F043E9B0383060BA7
9F08B3490D8860063374126512041704
169E0384060BAB9F08B349988766062A
7409650D041504519F0380060BCE9F08
B249108768062F74076510041304F49F
0382060B06A008B249AE866406427401
652204100464A1037E060B37A008B349
408661065B7402651C04110438A3037E
060B6CA008B349ED8568065E74FF6418
041004F8A4037C060BB5A008B3499B85
66066A74EE641D041504F7A6037B060B
23A108B3492D8563065C74E764190409
0405AA0375060B79A108B449AA846406
5A74DE641F040504EBAD0375060B91A1
08B449518468063274E0641F04FF03DE
B10375060BBAA108B549138461063E74
DA641D04FB0333B40373060B1DA208B4
49068468064074C3645F04040427B603
71060B6EA208B449F7836C064674CD64
5F04FD03F9B80371060B7AA208B549D1
8368064274CF646204FF034BBB037106
0B90A208B549B08366065A74CD646104
FF038CBB036F060BC4A208B649968364
065C74C3645F0403048ABC036D060BF4
A208B6498A8369066874C5646D040604
B8BE036D060B07A308B749728360065D
74BB646D0402041BC1036D060B1AA308
B749438366065E74C0646C0401046CC1
036B060B55A308B7491A8362066A74BC
64730403049FC2036A060BABA308B649
118363066874B0646E04040445C60367
060BFAA308B749F48266066974AB6470
04010438CA0364060B43A408B749BC82
68066974A0647104F90378CD0364060B
69A408B74964826C064F74A164700408
04C1D00367060B80A408B649FF816306
4A74AC648E040104ABD10364060BC3A4
08B649998162065374A0649004060419
D20362060B25A508B6492D8163065974
98648B040404C1D40364060B75A508B7
49788067064D748B648E04FD03CFD703
62060BA6A508B749E27F69064E748C64
9404F00376D90364060BD8A508B74943
7F5F064B7484648E04F5039DD9036206
0B1AA608B649A37E6506537485649104
F4039AD9035C060B6DA608B549F17D6A
06547474648F04F003E8DB0358060BB9
A608B5490B7D6306507473648704F203
68E00358060BDDA608B6492A7C620644
746D648204F803E5E4035A060BE8A608
B6495E7B63062E7466647B04F20386E7
0358060B11A708B649D67A5E0644746C
647F04F10399E80358060B5BA708B649
B17A67064B7462647904EE03B8E90353
060B99A708B749AE7A6B0651745C646D
04FA032BED0351060BCEA708B749A87A
6006557452647304F5034FF1034F060B
24A808B7499D7A620662744E647004F5
0345F5034D060B77A808B749A27A6606
5B7448647104F00317FA034B060BAAA8
08B749977A66065A7444647104EB0355
FF034B060BD1A808B749757A5D065E74
43647004F203EE020449060B0EA908B6
49507A620664743B647304EF03F60404
49060B54A908B749157A66065D743C64
6D04F003C9070442060B90A908B749DA
7960066A742C647F04F003A60C044006
0BB6A908B7499D79600666742C647B04
F2039312043E060BD2A908B749517964
06637435648004F603B817043D060B11
AA08B749FE78670674742C648604F003
F21B043A060B70AA08B649D57864066F
7420648B04F003D8200436060BC4AA08
B649B9786806757417648B04F8032027
0436060B08AB08B649AF78640671741E
649404F503592C0436060B3EAB08B549
947866066F740A648B04EC03C6310434
060B5DAB08B64980786006737407648F
04ED038E340434060B6AAB08B7494778
650663740B64AE04FD0369350434060B
88AB08B7498677680666740C64AC0401
0467370431060BC3AB08B64905776706
7A740464AC0404043F3A042F060BF0AB
08B6496F76660673740064B20401044F
3F042F060B10AC08B749E57560068274
00648B04F303BC42042D060B2EAC08B7
4978756206867401649304F803FA4504
2F060B4FAC08B749247565068774FD63
8E04F903E849042B060B89AC08B749D1
7464069C74F3638A04EE035A4E042C06
0BC5AC08B849857464069974E9639204
F703AC500429060BE6AC08B8492A7468
069E74ED639304EB0348520429060B20
AD08B849D57366069B74E8639004F203
0C550429060B77AD08B9497B7363069A
74E2638D04EA0374580423060BBAAD08
B9492A7361069674D863B904F2033561
0420060BFCAD08B949EF7261069574D9
63C304F103FB6A041E060B47AE08BA49
9F7265069B74CD63BF04F203DC74041C
060B93AE08BA49447266069F74BF63C0
04F203F07C041C060BD4AE08B949E871
5F06A674C163EB04DA037F830418060B
FFAE08B849CA7165069F74BB63E904DB
03BC89041A060B26AF08B949BA716506
A574B463EF04E603FF8E0418060B4CAF
08B949DE716406AE74A363ED04DD0339
930418060B61AF08B94918726006AA74
9E63E504DF03AE96041A060B74AF08B9
4968726606A9749E63F104E3032D9904
18060BA6AF08BA49D4725D06AA749963
E804E603E59B0419060BEBAF08B94928
735D06B3749B63EF04E6039E9F041606
0B31B008B94967736306B0749363EB04
E103EAA30414060B75B008B949897366
06B2749063E204DF03F7A70412060BC2
B008B9496C736406B2748863D804E103
74AB0412060B1DB108B94950736306B4
747363DD04E603F9AE040B060B7AB108
B9492E736506AC747463DF04E103DEB3
0403060BD1B108B9490F736406AA7464
630205EC03AEBA0403060B15B208B949
EB726506A7746963FF04E10312C20401
060B28B208B949DF7266069A746063FE
04E30341C70405060B38B208BA49E772
6806987463630405E403C3C704FE050B
81B208BA4946736806A07450631C05DE
03A7C904FA050BDBB208BB49F9736206
AB7450631A05EA03A3CF04F8050B24B3
08BA49CC746C06B67451632305DE0303
D404FA050B68B308BA4972756406BA74
46631A05E30355D504F8050BA4B308BA
4927766706C17443631E05DB0342D504
F6050BD3B308BA49D1765E06C2744263
2005DB03C1D904F4050B08B408BA4978
775F06C3743C632205E20340E004F405
0B4DB408BA490B786506C97446631F05
EB034DE704F2050B9DB408B949807864
06C77440631A05E7034CED04F2050BFF
B408BA49D8786406D0742E637605F603
F5F204F0050B60B508BA492F796606C9
742A637E05F30385F904ED050BA9B508
BB4951796706C67427637F05F503A500
05EC050BDDB508BB4960796806C27430
638105EC03CD0605E9050B14B608BB49
5A796606C7742B639605FF03D00A05EB
050B4EB608BA4969796606C6742B638D
05FF03230C05E9050B7BB608BA498779
6606C2742963920501047E0E05E9050B
A5B608BB498D796206CD7421638D05FF
03311205E7050BD5B608BA499A796506
D67421632F050104FE1505E5050B0AB7
08BB49B0796606D67419632E05FF03CB
1905E6050B5AB708BB49A7795F06DC74
1C6331050704EC1D05E3050BD2B708BB
49A9796106D4740C632F050104B62205
E3050B38B808BB49B5796106CA740463
3E05FD03602805E1050B7FB808BC499C
796306C374FA623B050104E72D05DF05
0BC9B808BC4998796806C174F8624505
0104A23205DF050B23B908BD498B7964
06C174EE62460502047B3705E1050B86
B908BC498F796706BA74E9624B052604
E53C05DD050BDDB908BD4992796906B6
74E66256051F04CA4205E2050B1DBA08
BC4976796406B574DD624D0527045947
05E1050B53BA08BC4973796706B674E0
6250052304494905DF050B87BA08BC49
57796706C174E86249051C04E14A05DF
050B99BA08BD4950796606BB74E26239
0530042D4E05DF050B9EBA08BD495979
6106C374E3623C052F04F94F05DF050B
D0BA08BD4951796C06CD74DB623E0535
04E94F05DF050B10BB08BC4946796806
C974D66243052E04EF4F05DF050B2FBB
08BC4948796206D674D5623C053B0421
5105DD050B59BB08BD4933796006D574
D8623F053E04875005E1050BA3BB08BD
4932796206D874D9623F054404A35005
DF050BDFBB08BD4942796706D674D462
410542045B5305DA050B0BBC08BD494D
796606E574C86245054E04D75705DA05
0B4DBC08BC4941796606E374D3623A05
5504575D05D4050BA6BC08BC49277966
06E274C96245055204626305D2050B10
BD08BC49ED786406D574C06242055204
9A6A05D3050B6BBD08BC49AF786006D0
74C0622D055904FE7105D0050BBBBD08
BD4971785D06CB74B56228055C046778
05D2050BF8BD08BD495B786806CD74B3
62350558042B7E05D2050BFFBD08BC49
71786206C774AD622F055D04628205D2
050B07BE08BC49CD786606C974A662B2
056404248205D2050B46BE08BC495A79
6706D074A462B4056B04C78305D2050B
90BE08BC49F0796206D074A362AF0573
046F8805D9050BB6BE08BC493E7A6506
D674A862B2056604DF8B05D6050BD7BE
08BC49577A6A06CE74A262AE056A0454
8E05D8050B0BBF08BC49597A6606D774
9C62BF057B047E8F05DA050B4BBF08BC
49317A6506DF749C62B6057A04BB9205
D8050B90BF08BC49A6796706E0749E62
BD057B04BF9705D6050BD2BF08BC49C2
786A06E274A162BF057B04789C05D405
0B0CC008BD499A776106E274A062AA05
8D04289F05D6050B4DC008BD495F7664
06DC749D62B005940450A005E1050BA5
C008BD49CD746306E9748F62AC059104
57A305ED050BE9C008BD4952736706D8
749162AC058A0400A805F0050BFFC008
BD49E5716206E07485621A06980450AC
05EB050B0EC108BD4990706206E1748B
621A069604CCAE05F8050B46C108BD49
206F6606DB7485622206A004B5B00516
060B8CC108BD49306D6606DD74896221
069D041FB40518060BC4C108BD49936A
6706E37484623B06AA041DB8051C060B
02C208BD49FE666706DD747E624006A8
0403BC051E060B45C208BE496C636206
DF7475624406A70451BF051C060B8FC2
08BD494A5F6806E7746C624006A90410
C1051E060BE7C208BD49385A6306E774
66625C08A8045CC30520060B56C308BD
498B546606CF7452625F08A4046AC605
29060BD9C308BD49CE4E6506BD744A62
6108AB0468C90527060B2DC408BD490D
496206A9743A626608AB0440CC052606
0B48C408BD49874360069B744D626108
A5046ACE052D060B46C408BC49F63E65
06937458624717F404EFCE0527060B43
C408BC49023B64068A746F624D17F604
31CE0529060B56C408BC4973376A068F
748F624C17FD04C7CD0529060B83C408
BD49783467068D74AD625017F804D2CD
052B060BC2C408BD49E03162069474BF
623120F8043DCE0540060B0AC508BE49
B62F68069874CD622820F70459CF0541
060B57C508BE49C32D60069374E6622E
20FA04B2D2053C060BA3C508BE492F2C
60069274E8622E20F504E5D4053C060B
ECC508BE49EF2A65068D74F46268172C
05CBD70545060B55C608BD49DC296206
8B7400636E17210514DB058F060BC5C6
08BF49EB28680681741663651727056C
DF05EF060B1AC708BF4918286A067374
3C636A172E0529E50513070B48C708BF
4959275F066D747263FE0E3F0589EB05
14070B6CC708BF49B6266A066074BC63
EE0E470546F0052E070B99C708C04925
266A0661742C64F70E5005D6F3054C07
0BCEC708C049B125690660748D64F40E
410560F7057D070B19C808C0493F2561
0660745B65B50C5D059CFA058E070B70
C808C149E424640667740C66BA0C5A05
D0FD0590070BB1C808C149972468066B
747966AE0C55059C0106A1070BDCC808
C1493F2466065174C366B40C56050305
06A7070B05C908C04901246206457423
67B60C5705460706A5070B54C908C149
CD235D064174AA67FB0871052C0906A7
070BB6C908C14996236A062F740168FD
086905520B06B0070B09CA08C1496723
640621744668FE086605E30D06B4070B
44CA08C2493F23630608748368FC086A
05800F06B0070B67CA08C24906236306
EE73D1684E076905291006B4070B94CA
08C249F0226606E373E8695007670502
1106B4070BDACA08C249C7226B06D373
A76A49076605A91006D2070B0FCB08C2
49AB226106C673196B51076505101306
DF070B50CB08C2499E226A06C373816B
AD064705A2150624080BB0CB08C2497D
226406B173F36BA70648058817063808
0BFECB08C2495E226006A673466CAF06
4A05151A063E080B3ECC08C2494B2260
069B73966CAD064C05FF1C062D080B7E
CC08C2493D2262068A73D66CDE06F804
D71F0643080BC1CC08C2492022690673
730C6DDC06FA04F2220691080B08CD08
C349172263066D733C6DDF06FD04F925
0612090B48CD08C249092269065D736C
6DDA06FC0464280666090B75CD08C249
F22161065073916DAD06A604B8290666
090B9BCD08C249EB215E064373B66DB2
06A904F9290646090BCFCD08C149D821
67063F73EE6DB006AA04062A062B090B
05CE08C149C52164063873306EAF06AB
04402A0635090B2ACE08C149B1216606
2C73666EAF06AD04F82B0644090B2CCE
08C149B02167062273886EA106890416
2E0640090B2DCE08C149A3215E061A73
BF6E9A068A04CD2E066D090B51CE08C2
49922160061173026FA0068C04412F06
75090B98CE08C249792164060A73296F
9C06870406310686090BDECE08C2497B
2162060773476F6C069004FB3206B509
0B13CF08C24981216406F472696F6B06
89046F3406E0090B47CF08C249672162
06E6728E6F6D068604923506FD090B93
CF08C24965216206E772CE6F69068A04
153606440A0BDECF08C2495C216106D6
72F46F9C06C204BE36066C0A0B17D008
C2495B216006C67226709F06C9045B38
06680A0B46D008C2494A216606BD7251
709C06C504853906590A0B7DD008C249
3E216406BA72BE709806C204443A0672
0A0BD1D008C3493A216206AE7227719E
069A04A33A06C60A0B22D108C3493C21
66069E726B7196069904453C06C60A0B
59D108C4492D215D069572A371A4069F
046E3E06C40A0B95D108C44924216606
8772DA71A1069C045C4006FA0A0BD3D1
08C449232163067D72137262068D04B6
4106100B0BFDD108C4491B2167067372
4F725E068404DC41061D0B0B21D208C3
492321680671727E725A068704A34106
340B0B48D208C4490C2166067272B072
60068C042B42062E0B0B7FD208C3490D
21650662720F737B066D046343061F0B
0BC4D208C4490D2169065B7248737F06
6A040944061B0B0B09D308C349FF2062
06587280737C066F04D444061D0B0B41
D308C449022168065072AC737C066A04
F546061F0B0B6AD308C449F420600650
72EC7380066604CD4806260B0B9CD308
C44902216A0651720A749F056A041D4A
06280B0BC1D308C449F5206A06427229
74A1056B04564B061F0B0BF1D308C449
E420600649726474980569046B4C0636
0B0B4FD408C449F12061063C7294749C
056B04674D064E0B0BA2D408C449E720
5E063D72BD740D056B04924E06500B0B
BFD408C449E62068063472DA740B0572
04B24F064E0B0BC9D408C449DD206706
2E72E7740B056604535006530B0BDED4
08C449D520600632720A750F056C0475
5006570B0B0AD508C549D72060062C72
48757E045504735006650B0B56D508C5
49D7206C062F727B757C045C04045106
6C0B0BA2D508C449D120600628728B75
800457046252066E0B0BC7D508C549CD
205D063272A47583045704E453066C0B
0BDAD508C549C9206C062C72BD75DC04
7704D15406700B0B10D608C549C8206A
063272F675DE046E046E5506840B0B68
D608C549BD205B062C721A76DF046C04
235606AE0B0BA7D608C649C22068062A
723676DB046D04EA56069F0B0BB7D608
C649C120650628725A76EB046D048557
069F0B0BC1D608C649BA206106237288
76F5047304BF5706AC0B0BDBD608C649
B82067062B72B376EF046F04E25706BF
0B0B0BD708C649C0206C063572DD76EF
046A04085806CC0B0B68D708C649B420
660630720377E9046A041558060C0C0B
01D808C649AC2063062B721D77C10467
044858062A0C0B9ED808C749AA206C06
22723077B9046A044D59061F0C0B01D9
08C749AB206A061B723F77BD046C04F3
5A061B0C0B3DD908C749AC2068061B72
5177C0046E047C5C06130C0B83D908C7
499F2063061B72647761047C04AD5D06
050C0BCED908C749A220620612727377
61047B04D45E06010C0BF7D908C749A7
206206147289775B047304FB5F06FF0B
0B10DA08C749942066061072A8775604
7C04C36006000C0B24DA08C7499E2064
061872DA77200479043D6106FD0B0B4C
DA08C7499C2067062172FC7720047804
B36106EE0B0B87DA08C649A22062062C
72127820047C04596206E50B0BC3DA08
C749992062062A721C781E047D042D63
06EA0B0BFBDA08C64995205F062C7226
781B048704F56306EE0B0B40DB08C649
A020620630723B781C048504276406F6
0B0B9CDB08C7499220600633724E7821
048F04A76306E80B0BFADB08C749A220
640635725D781D048904836306E50B0B
31DC08C74991206A063B726878110472
04626406E50B0B40DC08C749A3206306
377277780B0476041E6506EA0B0B60DC
08C649862062063E729F7808047B04DD
6406DF0B0BA2DC08C649912062064272
B4780A0478042B6506CA0B0BF3DC08C7
498A2065064272C47810046604EF6506
C10B0B36DD08C649882060064872D278
0D046604A66706BB0B0B56DD08C64993
2063065072DD780F046C045A6906C20B
0B69DD08C649812064065072F9780E04
66045C6A06C10B0B89DD08C649822064
0651720A7912046B04C76A06C50B0BB9
DD08C7498C206506557224790C046904
246B06BB0B0BF0DD08C7498D20640661
72357912046804D56B06BA0B0B25DE08
C7497F20690662723A790E046704B56C
06C10B0B63DE08C7498820640667724F
7909046504736D06B60B0BAFDE08C749
82206506647250794A047D04F26D06BA
0B0B03DF08C7497A2066067572627947
047D04336E06B90B0B44DF08C7498C20
69066F725B7954047A04E46E06BB0B0B
6CDF08C7498620610675726C7950047D
04A36F06BD0B0BA6DF08C74983206606
797293792F046F04337006C90B0B13E0
08C749792064067372A17927046704A9
7006E50B0B77E008C749712064067B72
AB792E046A04207106F90B0BA8E008C8
49792064067B72BC792A046D04917106
F00B0BC6E008C949752062068272C079
74047A04E87106FC0B0BE6E008C94975
2065068272CD7974048204237206050C
0B1CE108C9497D2062069072D9796A04
77045972060E0C0B62E108C949832067
069172EE796B047804A172061B0C0BB3
E108C949732068069072FA79E3038404
FA72061F0C0B04E208C9496A20640691
720F7ADF038D046C7306210C0B50E208
C949732069069572237AE1038F04D673
06250C0B99E208CA497B205E06937225
7AE20393043674062A0C0BE5E208CA49
762062069172347ADF036B04A474062E
0C0B42E308CA497720620695723D7AD8
0366041D7506390C0B96E308CA496F20
6C069A723C7ADC036D049D75063D0C0B
D5E308CA49632063069C72477AE10368
042E76063E0C0B0AE408CB4972206906
9D72507AE4038004A97606410C0B35E4
08CB496D2063069B72487AE00382040D
7706430C0B52E408CB4972206206A072
587ADC037C045D7706470C0B78E408CB
4959206606A372647AE30372049D7706
450C0BBEE408CB4973206506AD72767A
E0037504DB77064C0C0B14E508CB4969
206406A6728E7A1C047104377806520C
0B69E508CB496F206406A472917A1B04
6F04AC7806570C0BB0E508CB49622066
06A972A57A1D0471042A7906590C0BF5
E508CB495D206406AD72B47A1C046D04
8C79065D0C0B2AE608CC496A206206B0
72C57AF1036A04DE7906610C0B60E608
CD4978206306B072D67AEF036804247A
06680C0BADE608CC4973206706AD72D8
7AE7037404637A06680C0B05E708CC49
62206506BB72EA7AEF036B04B47A066C
0C0B58E708CD495B206406B272EA7AFE
036604257B06720C0BA5E708CC496A20
6406B872027B01046B04917B06760C0B
DDE708CC4968206106B8720C7BFD0365
04F37B06740C0BF2E708CD4966206406
BC72117B01046C04377C06720C0B00E8
08CC4968206406BA72287B2D046D043C
7C06740C0B13E808CC495D206406C272
3D7B2F046E04347C06740C0B41E808CB
495C205F06CB72537B34046B04327C06
880C0B8EE808CC4964205E06C9725A7B
30046604567C06A20C0BF1E808CC4957
206606C6726E7B00047804277D06AC0C
0B41E908CC4954206206D3727C7BFF03
7A04127E06BF0C0B84E908CD4955205D
06C972897B03047A04077F06DD0C0BD3
E908CD494F206106D3729E7B05047C04
EA7F061B0D0B27EA08CE4963206506CC
72A57B230499040281065F0D0B69EA08
CD4959205D06CD72AE7B1C0495044C82
068B0D0BABEA08CE4958206406D172C2
7B18049704778306E10D0BF7EA08CD49
64206606D172CC7B1E04930464840621
0E0B4CEB08CD4966206406D272D17B1E
049A040785064A0E0BA5EB08CE496A20
6A06D172DB7B05048C04B085064C0E0B
EFEB08CE4953206606CE72E37B03048F
049A8606590E0B32EC08CE4964206606
C972DE7BFD038904648706CA0E0B70EC
08CE4962205D06CA72EC7BFF038D04AC
8706210F0BB4EC08CF4957206306C672
E77BEE038604898706370F0B0BED08CF
4957205E06C572ED7BE2038404CB8706
900F0B6EED08CE494F206506C572ED7B
EC038C04658806B50F0BB7ED08CE4951
206906BF72ED7BEE039004E68806B50F
0BE8ED08CE494C206C06C272EE7BF103
92042E8906B50F0B33EE08CD495A206B
06BA72FD7BF6038D04838906AF0F0B90
EE08CD494F206506BC72147CF0038404
E38906B70F0BCEEE08CD4951206306AD
721A7CEF0389041C8A06BD0F0BFAEE08
CD494F206806A272157CDE038604088A
06CD0F0B3CEF08CD4959206506AF721F
7CD8038D040A8A06F50F0B8FEF08CE49
55206506AA72387CE3038E040C8A0614
100BD8EF08CD494F206206A6724B7CE3
0388043C8A0620100B0CF008CD495520
6906A772547CF2038D04968A0620100B
19F008CD4952205E06A2725D7CF8038C
04F38A060D100B27F008CD4957206206
AC72837CEF038B040F8B0645100B5FF0
08CD4955206606A672A97CF00385041A
8B0670100BB2F008CD4954206006AE72
C47C27046F04368B0674100B03F108CD
494F206006A972D97C2B047C04298B06
69100B4BF108CE4950206006AC72F37C
34047C04FE8A06F4100B92F108CE4953
206806A672087D30047F04D78A066E11
0BCAF108CE494E206406AC721F7D0C04
B704DB8A06D2110BFBF108CF494F2062
06AB72437D1604BC04C38A0689120B37
F208CF494F206106B072657D0B04B904
1A8A068D120B67F208CF494F206306B1
72717D0B04BA04368906C1120B80F208
CF493E206406A6727C7D0904B6044A88
06F6120B96F208CF4946206106B1728D
7D2E04E004728706E8120BB5F208CF49
45206806B572AD7D2804E1041887064E
130BCFF208CF4944206206B172C47D32
04D60447870680130BE2F208CE494F20
6406B272C97D2C04D8045587061A140B
F4F208CE494A206206B572C87D1104BA
04528706C8140B10F308CF4946206B06
B972D57D0B04B904608706FA160B2EF3
08CF4940206906B972F67D1004B40476
8806611A0B4AF308CF493F205B06C072
147E1704B204E58906FA190B56F308CF
4940206606B372277E1004C804828A06
12190B60F308CF4947206606B9722E7E
0C04CB048A8A06D1180B64F308CF4947
206106BA723B7E0C04CB04718A06A817
0B67F308CF4948206406BB72557E1204
C6041D8A064E160B6BF308CE494B205E
06C7726D7E2404A704AA89067C150B6F
F308CE4941206606C6728D7E1D04A704
3B8906B6150B71F308CE4944206206D1
72A77E1604A7040989064C160B74F308
CE4945205C06D172B67E1A04A5040D89
0612160B7AF308CE4944206606D072D2
7EFA037A049988068B150B7DF308CF49
3C206706E072EE7EF8037904F38706D4
140B83F308CF493E206A06E272097FFF
0376046A8706CE140B84F308CF493E20
6106E272187FFD038204EC860668140B
84F308CF4946206206E972257FFF0386
045F8606CC130B82F308CF4940206C06
F2723A7F01048904BF8506A8130B7EF3
08CE4941206206F9723E7F05048904C0
8506F4120B6BF308CE493E205D06FC72
3E7FFD038B048C8506FB110B56F308CE
4948206506F4723E7FDC038904C18406
2E110B29F308CE49422060060073547F
DD038704AF8306AB100B99F208CE4942
2060060373D57FE3038D045C8306600F
0B5CF108CD493F2066060673C57FDD03
8904128106AB0E0BA9EF08CD493F2062
061673BE7FEB036B04637B06880D0B3D
EE08CD49392060061C73B87FEB036D04
A47306430D0B0AED08CE492C2067062D
73F27FEF036504626D06D90C0B7BEB08
CE49382062063773FE7FEB037204D669
06790C0BB8E908CD49352062064E73F4
7F1B047904666806680C0B80E808CE49
3E2064065B73EA7F19047D042667065F
0C0B78E708CD49362061068073F87F24
047D04946606680C0B45E608CD493C20
600699731A801D047C04D06606540C0B
02E508CE4943206406BC730F801B047B
04FB6606560C0B4DE408CE4948206406
CC730E801A047A043A67062A0C0BDBE3
08CF4947206406DD73098020047A04AD
6706140C0B13E308CF495F206006F073
1B801F0475044B67062E0C0BD8E108CF
494F206806FD732C801C047C04FC6606
150C0BA0E008CF4956206B060E742780
23046A04136606190C0B8FDF08D0495E
2060061B742A801D046C04246506120C
0B72DE08D04959206406267428801D04
69049564061D0C0B42DD08D049522063
0633742C8023046D04526406150C0BEB
DB08D04959205E0636741F8031046604
F66306E30B0B52DA08D04957206A063E
742A802A047104826206A80B0BD1D808
D04957206206527430802E046604745F
06AE0B0B97D708CF495B206606517433
802C046504235D068D0B0B56D608CF49
592062065A7447804F046404FA5A0694
0B0B19D508CF495E20650668744E804E
046804DC58069D0B0BEBD308D0495B20
64066A745B804A0468045A58067A0B0B
74D208CF495D20620673746F80500464
042457062C0B0BE9D008CF496F206006
78747880B0046D04A653061F0B0BA6CF
08CE49612064067A747180AF04640404
5006260B0B56CE08CE49662060067E74
7E80A8046004B54D06D30A0BE5CC08CD
496C20650680747B80A8046A046C4A06
AE0A0BABCB08CD496820600685749880
4B056B04864606B20A0BA7CA08CD4973
20660695749B80550567044244069F0A
0B90C908CD497B20650698748C805105
6A04FD42068C0A0B5BC808CD497B2063
069274C480490570047A4106A70A0B1C
C708CD4989206406A874A08046056704
7941066C0A0BD0C508CD4991206706AA
74DA80D4057504BA4006110A0BAFC408
CE49A2206406BA74D880E30579047B3D
062C0A0BA5C308CF49AA206006A474AA
80D7057504DA3A06E1090B44C208CF49
A72066069F74DE80E005740455380637
090BBCC008CF49B0205C06B574AB80D0
06A204EF3106E0080B89BF08CE49C420
6806C2748580CA06A50442290615090B
3DBE08CE49C9206B0697746A80D206B5
045F240627080BA8BC08CE49D0206006
AD745180D206AF04121B0680070B36BB
08CD49D8205A06CD744680DB0BE004DC
090690070BDDB908CE49E5206606DE74
7780D80BD30402FF05F6070B7BB808CE
4909216806FF748680D60BD904F5FB05
52070B2CB708CE49252167060C752680
DA0BDE049AF60530070BDBB508CE4978
216A062A7508806A0BC704B5ED050A07
0B6DB408CE49EA2166065075C07F630B
BF04A8E4057B060B0FB308CE498A2263
066875867F690BCE0422D0055E060BC3
B108CD49462365065A75747F6B0BC904
38B805A0060B6BB008CE493B2460064B
75687F90078904D2AA0564060B35AF08
CD498225640653751C7F81077F043A9B
057A060B00AE08CD494D276A067E75DA
7E7F078B042E8E056F060BA2AC08CD49
DF2962069B75A17E88078B04D9850528
060B45AB08CD49A82D6006BB75567E8B
064A045B6B0549060BD4A908CC498331
6206C6751E7E02064304385C052F060B
5EA808CD49A9356806D475C57D070642
04D14D051C060B2AA708CD49C9396B06
D1757A7DF9054004FF250520060B0AA6
08CD49063E6106C275357DFB054604E4
07053A060BC8A408CD49AB426506C975
FC7C04051704ADFC042F060B73A308CD
494A476606C075D57CFB040E043CF704
25060B4DA208CD49CE4B6706C875AD7C
FB040C04B0D5042E060B3AA108CD4993
506806CC75697CFA040F04C4BD043606
0B27A008CD4923556206D5751D7C8A04
04043EBC0436060BEC9E08CD49E95867
06B575ED7B8F040404F5B30442060B6E
9D08CD491E5C600686759A7B9004FF03
DE91044D060B079C08CD49025F6B0668
75617B8E04FB036F5C0447060BD49A08
CD49586268067275137B4E040204653F
0449060BB99908CD49B06567066F75C6
7A4A04F8034D320452060B819808CD49
9F6864067175987A52040104A0260453
060B349708CC490C6B61066675457A50
04F9031F1D045C060BD89508CD49776D
6A0643750D7A1F04FF03600E0464060B
7F9408CC49986F63064A75BF791F0404
04CDF90364060B529308CC49B9716106
4C7582791A04020411EC035C060B2C92
08CC49BB73670651754F791D04FD03AA
EB036D060B109108CC49897563066575
1A791B04FF0320E4037B060BEF8F08CC
49CF7662066A75D578CE030E047BCE03
7E060B958E08CC49657864065675B778
D203100492BD038B060B358D08CC4911
7A630640758378CB030D048FA7038606
0BFD8B08CC49B07B660620754D78CD03
0904269C0382060BD28A08CC49927D63
06F7740278C003140451990382060BA2
8908CC49FD7E6306C774CD77BE030F04
B19A0392060B708808CB4949806006A4
749D77C0030B049B8D0393060B4E8708
CB4952816606AC745B77B7031104017C
0395060B2E8608CB49E3826506C4742A
77C20310044E71038F060B198508CB49
65846106D874EA76BE0310048F720391
060B1A8408CB49A8856406AB74B476BC
030704E1760393060B338308CC49A086
6606AE747176B7031304B7740397060B
6C8208CD4964876806CF743C76BD0304
042F6D039C060BD28108CC4929886306
0275F575C103FE03B264039E060BB581
08CC4907896406F474D175C00304040A
5C03A2060B598108CC49AC896206BE74
9975C003FC03D45103A0060BA58008CC
49718A68068F747575B7030004374A03
A0060BF27F08CC496A8B6806ED746775
C3030104E94703A2060B407F08CC494F
8C630647753E75C2030404BA4603A206
0B5F7E08CC49358D6A0667751075B803
0404A24503A2060B0E7D08CB49188E62
0692750775C3030104AB4303A0060B3C
7B08CB49B28E66069975EC74B1030104
5C4103A4060B467908CC494A8F6206AE
75C574AC0304042F3D03A2060BCA7708
CC49FB8F6206CD75C574AF0306040738
03A6060B197708CC49B9906506B97592
74A9030104653303A8060BE97608CB49
BD916606AB756D74B8030604742E03A7
060BCD7608CB49C4926606CA753074B7
030604EC2903A8060BC17608C949D493
5F06D9751574BE03FF03092703AB060B
D57608C949D2946406FD75FB73BA03FF
03F22403A8060BE27608CA4991956206
0676E273BC03FA033F2303AB060BD976
08CA49449664061176BB73C303020406
2203AB060BC67608CA49B79661060276
8D73C403FB03312203AB060B427608CA
4919976006C8758573BA030304892203
A9060BC77408CA4958976206AC756673
CB031F04DE2203A8060B037308CA4968
97620662752074CB031D04D12303CB04
0B5E7208C9498097630694745D75CE03
22044825032B030B657208C949799760
0619747F75CC03220422270301030B64
7208CA49859766060874CC73F8021C04
902903ED040B627208C949B897690606
743873F7022204EE2C03ED050B627208
C94988976506EB733173F50223041934
03A6060B637208C9499B966606A17329
73F1021D04613903AB060B637208C949
2B9567068173FE72F0021D043F3C0363
040B647208CA49A89367066673EC72A0
0280039D3E036B030B637208CA490C92
64064573BC729C0285032A410373030B
637208CA49D09068063273AB72A40287
038B43033A030B637208CA4919906406
1A7303739E027E035846034D030B6372
08CA49D78F6606E7728873D902B403AD
48033C030B627208CA49F08F65061873
1C73DA02B303CE4A0340030B637208CA
493E9066063A73CA72D002A903204D03
44030B627208CA49B790660630736E72
CD02A903114F033E030B627208CA4950
9168066D73FF71D602E103</Data>

   <DataCRC>1216e4c1</DataCRC>

   <BytesSent>20539</BytesSent>

</SBEDataUpload>
</InstrumentRawData>
</SBEDataUploadFile>
