<?xml version="1.0"?>
<!-- SCPlusV2_RS232 -->
<SBEDataUploadFile>
<ApplicationData>
<Seaterm232>
<SoftwareVersion>2.8.0.119</SoftwareVersion>
<BuildDate>07-Nov-2018</BuildDate>
</Seaterm232>
</ApplicationData>
<InstrumentState>
<HardwareData DeviceType='SBE19plus' SerialNumber='01907809'>

   <Manufacturer>Sea-Bird Electronics, Inc.</Manufacturer>

   <FirmwareVersion>3.1.8</FirmwareVersion>

   <FirmwareDate>Mar  9 2016 16:22:29</FirmwareDate>

   <CommandSetVersion>1.4</CommandSetVersion>

   <PCBAssembly PCBSerialNum='120721' AssemblyNum='41054J'/>

   <PCBAssembly PCBSerialNum='120715' AssemblyNum='41967A'/>

   <PCBAssembly PCBSerialNum='116699' AssemblyNum='41606'/>

   <PCBAssembly PCBSerialNum='120719' AssemblyNum='41059D'/>

   <MfgDate>28-Apr-2017</MfgDate>

   <InternalSensors>

      <Sensor id='Main Temperature'>

         <type>temperature0</type>

         <SerialNumber>01907809</SerialNumber>

      </Sensor>

      <Sensor id='Main Conductivity'>

         <type>conductivity-0</type>

         <SerialNumber>01907809</SerialNumber>

      </Sensor>

      <Sensor id='Main Pressure'>

         <type>strain-0</type>

         <SerialNumber>10586018</SerialNumber>

      </Sensor>

   </InternalSensors>

   <ExternalSensors>

      <Sensor id='volt 0'>

         <type>pH</type>

         <SerialNumber>27-0363</SerialNumber>

      </Sensor>

      <Sensor id='volt 1'>

         <type>ORP</type>

         <SerialNumber>27-0363</SerialNumber>

      </Sensor>

      <Sensor id='volt 2'>

         <type>OXY</type>

         <SerialNumber>43-0434</SerialNumber>

      </Sensor>

      <Sensor id='volt 3'>

         <type>PAR</type>

         <SerialNumber>1122</SerialNumber>

      </Sensor>

      <Sensor id='volt 4'>

         <type>ECO AFL/FL</type>

         <SerialNumber>FLNTURT-2496</SerialNumber>

      </Sensor>

      <Sensor id='volt 5'>

         <type>ECO-NTU</type>

         <SerialNumber>FLNTURT-2496</SerialNumber>

      </Sensor>

      <Sensor id='serial'>

         <type>not assigned</type>

         <SerialNumber>not assigned</SerialNumber>

      </Sensor>

   </ExternalSensors>

</HardwareData>
<StatusData DeviceType='SBE19plus' SerialNumber='01907809'>

   <DateTime>2019-07-29T16:10:52</DateTime>

   <LoggingState>not logging</LoggingState>

   <EventSummary numEvents='0'/>

   <Power>

      <vMain>12.3</vMain>

      <vLith>9.0</vLith>

      <iMain>63.1</iMain>

      <iPump>39.9</iPump>

      <iExt01>19.0</iExt01>

      <iExt2345>36.2</iExt2345>

   </Power>

   <MemorySummary>

      <Bytes>44160</Bytes>

      <Samples>1920</Samples>

      <SamplesFree>2858868</SamplesFree>

      <SampleLength>23</SampleLength>

      <Profiles>4</Profiles>

   </MemorySummary>

</StatusData>
<ConfigurationData DeviceType='SBE19plus' SerialNumber='01907809'>

   <ProfileMode>

      <ScansToAverage>1</ScansToAverage>

      <MinimumCondFreq>5</MinimumCondFreq>

      <PumpDelay>45</PumpDelay>

      <AutoRun>no</AutoRun>

      <IgnoreSwitch>no</IgnoreSwitch>

   </ProfileMode>

   <Battery>

      <Type>alkaline</Type>

      <CutOff>7.5</CutOff>

   </Battery>

   <DataChannels>

      <ExtVolt0>yes</ExtVolt0>

      <ExtVolt1>yes</ExtVolt1>

      <ExtVolt2>yes</ExtVolt2>

      <ExtVolt3>yes</ExtVolt3>

      <ExtVolt4>yes</ExtVolt4>

      <ExtVolt5>yes</ExtVolt5>

      <SBE38>no</SBE38>

      <WETLABS>no</WETLABS>

      <OPTODE>no</OPTODE>

      <SBE63>no</SBE63>

      <SeaFET>no</SeaFET>

      <GTD>no</GTD>

   </DataChannels>

   <EchoCharacters>yes</EchoCharacters>

   <OutputExecutedTag>yes</OutputExecutedTag>

   <OutputFormat>raw HEX</OutputFormat>

</ConfigurationData>
<CalibrationCoefficients DeviceType='SBE19plus' SerialNumber='01907809'>

   <Calibration format='TEMP1' id='Main Temperature'>

      <SerialNum>01907809</SerialNum>

      <CalDate>24-Mar-19</CalDate>

      <TA0>1.217923e-03</TA0>

      <TA1>2.816693e-04</TA1>

      <TA2>-1.603333e-06</TA2>

      <TA3>1.984146e-07</TA3>

      <TOFFSET>0.000000e+00</TOFFSET>

   </Calibration>

   <Calibration format='WBCOND0' id='Main Conductivity'>

      <SerialNum>01907809</SerialNum>

      <CalDate>24-Mar-19</CalDate>

      <G>-1.005893e+00</G>

      <H>1.268163e-01</H>

      <I>-1.515604e-04</I>

      <J>2.671373e-05</J>

      <CPCOR>-9.570000e-08</CPCOR>

      <CTCOR>3.250000e-06</CTCOR>

      <CSLOPE>1.000000e+00</CSLOPE>

   </Calibration>

   <Calibration format='STRAIN0' id='Main Pressure'>

      <SerialNum>10586018</SerialNum>

      <CalDate>11-Mar-19</CalDate>

      <PA0>4.565618e-02</PA0>

      <PA1>4.850951e-04</PA1>

      <PA2>-2.883271e-12</PA2>

      <PTCA0>5.252467e+05</PTCA0>

      <PTCA1>1.223042e+01</PTCA1>

      <PTCA2>-3.567450e-01</PTCA2>

      <PTCB0>2.516687e+01</PTCB0>

      <PTCB1>3.750000e-04</PTCB1>

      <PTCB2>0.000000e+00</PTCB2>

      <PTEMPA0>-5.487846e+01</PTEMPA0>

      <PTEMPA1>5.537568e+01</PTEMPA1>

      <PTEMPA2>-5.867271e-01</PTEMPA2>

      <POFFSET>7.140000e-01</POFFSET>

      <PRANGE>1.600000e+02</PRANGE>

   </Calibration>

   <Calibration format='VOLT0' id='Volt 0'>

      <OFFSET>-4.920000e-02</OFFSET>

      <SLOPE>1.248122e+00</SLOPE>

   </Calibration>

   <Calibration format='VOLT0' id='Volt 1'>

      <OFFSET>-4.784000e-02</OFFSET>

      <SLOPE>1.248871e+00</SLOPE>

   </Calibration>

   <Calibration format='VOLT0' id='Volt 2'>

      <OFFSET>-4.864632e-02</OFFSET>

      <SLOPE>1.248714e+00</SLOPE>

   </Calibration>

   <Calibration format='VOLT0' id='Volt 3'>

      <OFFSET>-4.743790e-02</OFFSET>

      <SLOPE>1.248571e+00</SLOPE>

   </Calibration>

   <Calibration format='VOLT0' id='Volt 4'>

      <OFFSET>-4.671263e-02</OFFSET>

      <SLOPE>1.248951e+00</SLOPE>

   </Calibration>

   <Calibration format='VOLT0' id='Volt 5'>

      <OFFSET>-4.871053e-02</OFFSET>

      <SLOPE>1.249136e+00</SLOPE>

   </Calibration>

   <Calibration format='FREQ0' id='external frequency channel'>

      <EXTFREQSF>1.000014e+00</EXTFREQSF>

   </Calibration>

</CalibrationCoefficients>
<EventCounters DeviceType='SBE19plus' SerialNumber='01907809'>

   <EventSummary numEvents='0'/>

</EventCounters></InstrumentState>
<Headers>

cast   2 29 Jul 2019 11:39:20 samples 362 to 757, avg = 1, stop = mag switch

</Headers><InstrumentRawData>
<SBEDataUpload startAddr='8303'>

   <Type>1</Type>

   <DataFormat>SEACATPLUS0</DataFormat>

   <Bytes>9108</Bytes>

   <Data>
D861030A030BCE73084A4D1399408A06
861B52B8028D03D7610320030BCE7308
4A4D0999788902865C54BB029003D461
031C030BCC73084B4D1B99D798E38532
56B3028B03D161031A030BCD73084B4D
15994189C085ED57E8018503D1610323
030BCD73084B4D0F99DE88C585FD57E7
017E03D5610329030BCF73084B4D2099
7F88C1859E59E6017A03DC61032B030B
CE73084B4D19990586B985E85AE2017E
0302620329030BCF73084B4D1299F384
AE85BE5BE6017C034262033A030BCD73
084B4D2499E0869B85B75C0603580477
620338030BCC73084C4D1B9948909D85
975E060358049B62032F030BCB73084C
4D0C998D8DA585356004035904AB6203
2F030BCD73084D4D2F99CD92A485AD61
08035D04AF620331030BCB73084D4D0F
99C594A28532635001C504A862033403
0BCD73084E4D1999D397A38596645401
C304A2620329030BCC73084E4D119982
9C9F85F7655A01C2049C620327030BCC
73084E4D1399AFA2BD8567685301C904
9362031E030BCC73084F4D159982A5CE
846B965F0362026C61034A050B007408
4F4D2B9997A9C086000068036102015A
03EB060BC874084F4D2A99B2AE458E6E
6B650360025C520309080BDF75084F4D
19994FB1B995EF6C6A036102EB4C0309
080BD97608504D11994BB3CF9B2F6D96
02FE0BBB480309080B9C7708504D2299
64B4959FAC6C9302010CA7450307080B
647808514D3B9936B363A21E6D950201
0C9A440305080B1B7908524D819930B4
B9A41D6D9602050C52440303080BB779
08524DCE99469F18A6EA6CA0076A04E1
4403FF070B3D7A08524D4C9A2EAFD0A6
D06C9C076804264603FC070B947A0852
4DCC9AAFAB2DA77E6C99076604BF4603
FC070BDD7A08514D3F9BF3AD3AA7996C
96076D04434703FC070B567B08514DB0
9B26B72BA7B96C9C076704A44803F607
0BA37B08514D1C9C8CABEDA6C86CF107
5904AC4A03F2070BDD7B08524D769C96
A4B7A6DE6CF7076004EE4B03F6070B1E
7C08534DDD9C74B57CA6116DFA075504
934C03F8070B4C7C08534D4C9D3DB261
A6A76FF5075A045A4D03F8070BAB7C08
534D5C9D03A258A60370FE075904A74E
03F8070B117D08534DCF9D7E9E22A62C
7000085B04905003F6070B587D08534D
889EE8A9F3A53870FA075104405203F4
070B877D08534D309F39A0BAA54070FA
075704505303F4070B957D08534DA69F
44A974A54E701E0872040D5403F4070B
987D08544DE09F5AA530A54C701C0867
04B35403F4070B957D08544D9B9F25A5
F7A4597013086704525503F6070B917D
08554DE59E62A8CAA4547018086804D9
5503F2070B957D08554D699E23A49DA4
50702B0856043F5603F2070B987D0855
4D289E07A387A451702C085A04865603
F0070B947D08564DAF9E98A562A44B70
28085E04C45603F0070B8E7D08564D78
9F6DA551A4467029085804F15603F207
0B987D08574DE89FBEA429A442703608
6804135703F0070BA17D08574DF19F1D
A70DA4377034086704255703F0070BA2
7D08574D9F9F51A5E6A3307037086604
2C5703F2070BA37D08584DEB9E83A3C6
A3367036086B041C5703F2070BA97D08
584DE89D2FA59BA32E7036086204DF56
03F2070BAC7D08594D959CC1A877A32C
7073086804765603F4070BAC7D08594D
0A9BDEA15FA321706F086704045603F2
070BAC7D08584DAB99319F48A3207076
086104AD5503F2070BAE7D08594D6398
1EB32CA3197076086904675503F4070B
AD7D08594D2E9709A314A30C70B3086D
04265503F4070BB07D08594D1F968FA0
FAA21070B1086804E75403F4070BAD7D
08594D6B956AA1DAA20870AE086604A7
5403F2070BB07D08594D7F95F9A4C9A2
FF6FB1086B046F5403F2070BB57D0859
4D4C964AA7A7A2F96F8E086D043D5403
F2070BB77D08594D9E970FA88AA2F46F
7F0865040D5403F4070BB57D08594D1E
9961AA6DA2EE6F80086804DE5303F207
0BAE7D08584D919A77AB52A2EE6F8308
7204BB5303F4070BAC7D08594DED9B1D
A435A2E16FD9086904AA5303F4070BAA
7D08594D519DE1A71DA2E56FCF086604
A85303F4070BA97D08594D029EF3AA02
A2DC6FD1086604A85303F2070BA97D08
594DD29EE8A3EAA1D36FCB086704A653
03F2070BA97D08594D639F47A8D2A1C9
6FD0085C04AA5303F2070BA47D08584D
D39F77A3BDA1C56FD3086004A85303F0
070BA37D085A4D28A045A79FA1C16FD2
086004995303F2070BA47D085A4D63A0
56A788A1BA6FD4085804895303F0070B
A27D085A4DA2A0F0A770A1BE6FD20859
04825303F2070BA47D085B4DD3A091A2
63A1B86FD5086A048C5303F2070BA47D
085B4DD5A00AA14DA1B56FD808610491
5303F2070BA37D085B4DB7A08FA639A1
AB6FD2086204965303F2070BA07D085C
4DA1A0E6A627A1B06FD3086804995303
F4070B997D085C4D7DA0BBA712A1A56F
F5086E049D5303F2070B917D085D4D59
A031A7FFA09E6FF10867049D5303F207
0B907D085D4D49A0E1A4F4A0A16FF108
6B048F5303F0070B957D085D4D35A000
A9E4A09A6FEE086504815303F2070B96
7D085D4D2DA084A5D4A0996F04096804
785303F0070B937D085D4D34A06CA3BC
A0936F00096604745303EE070B907D08
5D4D35A07FA4ABA0896F06096D047053
03EE070B8D7D085E4D2BA08EAB8DA090
6F02096504735303F0070B8E7D085E4D
00A0DEA385A0876F03097904695303F2
070B8B7D085E4DEF9F73A66EA07E6F00
097304615303F2070B847D085F4DC89F
83AA68A07E6F04097604615303F2070B
857D085F4D8E9FA1AC55A07A6F030976
045B5303F0070B8B7D085E4D249FC5A5
42A0796F23097504565303F0070B967D
085F4D779E4EA732A0786F200972044F
5303F0070BA27D085F4DC09DBBAA26A0
6B6F21097B04475303EE070BA37D085E
4DF49C4AA919A0686F1E097D04425303
EB070B9F7D085F4D599C8BAA11A0656F
1A097304425303EB070B977D085F4D95
9BF8A5FF9F596F1B097704425303EB07
0B957D085E4DFB9A9DA1F09F626F1D09
7804425303EB070B947D085F4D2E9A00
A7E29F586F22097504415303EC070B91
7D085F4D6D999EA3E29F5B6F20097804
3E5303EB070B8D7D085F4DB0980FAACF
9F4E6F11097A04395303EB070B8A7D08
604D029849A7C59F546F0C097D043653
03EE070B8B7D08604D5A971FA7B69F4D
6F08097304315303EB070B8F7D08604D
B09643AAB09F436F120977042A5303E9
070B927D08614D259665A7A59F416F31
097004265303E6070B767D08614D8395
23A4A59F436F320976042B5303E3070B
5B7D08614DF59420AAA39F376F300979
042E5303E7070B5E7D08614D55945CA5
9F9F396F310973042B5303E5070B5F7D
08614DA693EDAB989F356F210968042A
5303E7070B5D7D08624D059330A68A9F
356F28097104295303E6070B817D0863
4D799276AA7F9F246F1B096B04295303
F0070BEE7D08624DF39109A4429F256F
22096904295303F0070B467E08634D7B
917CA8039F236F44097B042B5303E907
0B917E08644D0D92EEA5E69E116F4209
7F04295303E9070BC87E08654D2592DE
A4C29E0B6F45097C04265303E3070BD9
7E08654D4492ABA5969E046F44097904
1F5303E2070BE57E08654D4A929FAE87
9EF96E420975041A5303E9070B387F08
654D5292FC9E8C9EDE6E7D0977041553
03EE070BB87F08654D6F9238A16E9ED3
6E7E097904115303EE070B258008654D
FD92F3A1609ED96E7E0979042A5303E9
070B718008654DE593C99C369ED16E7E
097B048C5303EA070BAF8008654DD994
059D1E9EC76E8F098604ED5303E7070B
FA8008654D5D956CA0109EC26E8F0984
04525403E3070B258108664D9295E59E
079EC56E95098704805403DD070B3F81
08654D8D95159CF49DB76E8E098E0486
5403DA070B428108654D4F95E39BE29D
B16E260A87047F5403DF070B54810864
4D0B95269FDE9DB46E330A8504925403
DF070B918108654D8A94409ED69DA66E
270A8D04BA5403E1070BD78108654D28
94E89CD69DA86E290A8704CD5403E507
0B3D8208644D1094009FB79D996E5E0A
7704EB5403E7070B9B8208654D379419
9B939D936E5D0A7704195503E5070BD5
8208644DB794FF9A669D916E570A7A04
6C5503DF070BF08208654D4D95C49D46
9D8E6E5B0A7704BF5503DD070B0C8308
654D9895F29C319D8E6E8A0A7A04F555
03DD070B348308664D9695D89A2C9D7E
6E830A7A040D5603DF070B5C8308664D
4795B49A1B9D7A6E7F0A7C041F5603DF
070B988308664DC094349B199D7D6E80
0A7104305603DF070BC98308664D1E94
BE9A139D736E8A0A7404445603E0070B
008408674D70935599009D746EFE0A87
04565603DF070B388408674DD7921899
EA9C646EFC0A8704695603E3070B8284
08684D5492189AD59C5F6EF10A88049B
5603E5070BD28408684D0A92ED97A59C
556EF40A82040C5703E5070B1C850869
4DD191F296899C556E550B7C048D5703
E5070B688508694D8E91AD97669C506E
520B7604125803E0070B938508694DC8
91E6974D9C526E580B75049A5803DF07
0BAD8508694DC99176963A9C436E540B
7404105903D8070BB98508694D889100
97209C3F6E360B7C047A5903D8070BC8
85086A4D2591DA97149C386E380B7404
C45903DA070BF185086A4D9C90F3950C
9C346E360B7804DD5903DD070B268608
6A4DEA8FC895F59B2D6E380B7B04F859
03DF070B5A8608694D308F2B96EF9B2C
6E710B65041A5A03E1070B9B86086A4D
758ED294CE9B236E6A0B6604465A03DF
070BD686086A4DC48D4094B69B236E70
0B6704645A03DF070BFF86086A4D3F8D
1994A09B1F6E730B6104735A03E1070B
1C87086A4DC78C4294909B216E530B66
04915A03DD070B2C87086A4D6E8CF893
779B1A6E5A0B6804C05A03DA070B3E87
086A4D218CD393669B156E540B6504E6
5A03DD070B5E87086A4DB98B5E93629B
146E560B6404FD5A03DD070B9487086A
4D5B8BF5924E9B136E4B0B64041F5B03
DF070BCF87086A4D068B80923A9B026E
E60A68046B5B03E1070B0188086A4DD6
8A3092149B056EEB0A6804B45B03E207
0B3B88086A4DCC8AA991F99AF66DE80A
6F04015C03E3070B7B88086A4DE28A22
91CD9AF56DE70A6A04415C03E3070BA4
88086B4DFF8AB990C09AF06D9C0B7304
5C5C03DF070BC188086B4D378BE090AB
9AEB6DA00B7204965C03DD070BD08808
6B4D6E8B85909A9AE96DA70B7C04ED5C
03E0070BF188086C4D948B33908D9AEB
6D9D0B7704295D03E1070B2289086B4D
7C8BE28F859ADF6D5C0C6604605D03E1
070B4F89086C4D598B548F759AD76D5F
0C6304AF5D03E3070B8789086C4D248B
C38E629AC76D600C6104015E03E1070B
BC89086C4DEC8A828E469ABF6D620C68
043F5E03DF070BDC89086D4DD08A7A8E
299ABC6DC00D6B04455E03DF070BF289
086D4DBD8A358E1D9AB66DBA0D690456
5E03DD070B088A086D4D9F8ADF8D089A
B36DBB0D6A04685E03DF070B2B8A086C
4D738A948DFD99A56DBC0D65047A5E03
E3070B5A8A086C4D358A2B8DD799A26D
060E6604A65E03E1070B888A086C4D1A
8AA28CAB99946D130E6F04F45E03E007
0BC58A086C4D098A408C7299896D0A0E
6D044B5F03DD070BEE8A086C4D158A0A
8C3299876D0B0E6804525F03DF070B0A
8B086C4D398AD58B0999806D0B0E6404
565F03DD070B238B086C4D658AA28BDE
98726DF20D6A04675F03DD070B328B08
6C4D7F8A978BB898456DED0D6404765F
03DA070B468B086C4D628A628B8E9824
6DEA0D6504875F03DF070B728B086C4D
388AB68A7398156DE30D6204975F03E1
070BB08B086D4D018A558A56980F6D08
106804D65F03D2070BDD8B086D4DC089
298A2698026D0E1064049E6103D0070B
F88B086D4D108AF889F897D46C11106F
04396803D6070B0F8C086D4D978CBD89
D997C46C0C106604A36E03D7070B208C
086E4D8593BC89B297B36C141174047B
7203D6070B2E8C086E4DD59A68899597
A86C0F1171049F7403D6070B4F8C086E
4DE9A0048987979C6C15117604DE7503
D4070B798C086F4D4CA5BA887B978A6C
12117B04F77603D4070BA48C086F4D5F
A862887097916CBF1482041A7803D207
0BD38C086F4DAEAAF5876397906CB914
8604467903D3070B098D086F4DD1AC7F
874A97896CB9148804627A03D2070B41
8D086F4DB0AE17873A97716CC0148404
567B03CE070B748D08704D5FB0AC862C
97666CE5139A04867C03CE070B9D8D08
704DDDB166861397A06CE0139704857D
03CE070BB98D08704D0EB345860997C5
6CDC139804F37D03CE070BC88D08704D
E7B32C86F396EA6CE61395043C7E03CD
070BDB8D08704D9FB4FA85EE96EF6C42
139904EE7E03CC070BF28D08704D0FB5
BA85E996FD6C44139704E07F03CC070B
178E08704D59B53985E196F26C421393
043B8103CC070B538E086F4D3DB5AE84
DE96E86C401399047E8203DF070B918E
086F4DD5B44184D196DE6C42139C04F3
8403DB070BD48E086F4DECB38A83B596
D56CEA12A9049A8703D4070B158F0870
4D95B224838696CC6CEA12AB042D8A03
D8070B448F08704DA7B0F0825596B96C
E912A704878C03DA070B5B8F08704D27
AEDD822C96B06CEA12A5044C8E03D807
0B618F08704D72ABD782FC95B76C2715
AB04F78E03D8070B638F08704DFEA8D5
82E395B06C1C15A604758E03D9070B68
8F08704D8AA69982C595AE6C2415A704
6F8E03D6070B888F08714DBDA44A82C1
95A36C1715A704DC8E03D8070BAB8F08
714D5FA3F181A5959A6CE5169A043C8F
03D8070BCF8F08714D66A29D8191955C
6CEF169904C28F03DA070BEE8F08714D
AAA174816F95436CEB169C04E29003D6
070B0E9008714D0EA1158159950F6CE8
169704869103DB070B289008714D6DA0
12812E95FF6B5E1598042F9203D8070B
2D9008714DC39FFA800D95E56B5C15A1
04C89203DA070B4B9008724DF39E5F80
EE94CD6B65159F04539303D6070B8290
08724D2C9EF47FD394B66B5C158F04DD
9303D4070BB79008724D7F9D7E7FB794
A86B5A1598042F9503CD070BEA900872
4DC39C247F8C949A6B6A169904279703
D0070B109108724DE09BD57E6E94916B
69169E04939803CE070B339108724DD5
9A837E5394916B6D169504B49903CE07
0B549108724DDC992F7E32947A6B6716
9304E59A03D0070B7C9108734DC798B7
7D1D947A6BDB179704149C03D0070BA7
9108734DF797747D0094726BDE179604
E29D03CD070BC99108734D4D971B7DE3
935B6BE0179804BD9F03CC070BEB9108
734DB596C57CD0934C6BDE17990492A0
03CC070B0A9208734D35969A7CB49340
6B8B17A70495A003CE070B1B9208734D
A5956E7CA293396B9117A204C0A003CC
070B299208734D1095467C8A93256B93
17A504F6A003CD070B409208734D7D94
E47B7593176B9117A5045FA103CC070B
679208734D28949F7B6193146B0F18B9
0447A303CC070B869208724DCA935D7B
4C930A6B0418AF0413A603CC070BA592
08724D7693077B4093F66A0B18B40478
A803C5070BC79208724D0693BD7A2493
FD6A0818B80469AA03C7070BE4920872
4D6092977A0C93F36ADB19B904ACAB03
C9070BF99208734D4C91687A0693EC6A
D819B7040FAC03C9070B189308734D17
90147AEE92E16AD019BA0460AC03C507
0B379308744DC98EEE79D792D26AD019
B5042BAD03C7070B549308734D8C8D8D
79C592D16AA41ACB04E7AD03C5070B7C
9308734D788C3D79B092CB6AA81ACF04
69AE03C5070BA69308744D7C8BDF78A1
92BC6A9F1AC604B4AD03C7070BD29308
744D738A5D788792B26AA11AC50439AD
03BF070B139408744D9589B4777692A5
6A9F1AC70470AE03BB070B549408744D
9D8856775392A16AB51CC50491B203B8
070B829408744DA487ED763892966AB9
1CC70499B703B8070BA79408744DA086
A57623928C6AB21CCB04FEBB03BE070B
CF9408744DF1843C760792816AB11CC3
047DBF03BD070BFB9408754DA182A875
EF91806A141FC5045EC203BD070B3D95
08754DDB7F1575DB91786A191FCB0441
C503C7070B6D9508764DF57CCE74B591
676A161FC00491C803CC070B8E950876
4D9B7A6E749C91676A181FC304C5CB03
CE070BB79508754D1C7917748891586A
7A20C404E4CE03D5070BDE9508754DE2
77B8736A91596A7A20C80422D203D807
0B0B9608754D417624736391506A7920
C90422D503DD070B379608754DAD73F5
724891446A7D20CD040DD803E5070B54
9608754D4B70AE723291416A1522B804
E7D803EE070B759608754D1C6C30721E
913D6A1722B604D4DA03FA070BA89608
754D5D67B0710F91316A1522BB049DDE
0309080BD89608754D33624C71019118
6A1922B9041AE30314080B019708764D
E25DEE70EE90156ACA21B40482E70323
080B2E9708764DEA597170D690156AC5
21B10485EB0336080B509708764DE655
5F70BF900C6AC121BA0464EF033A080B
5E9708764DCC512C709990066AC621B4
04ABF20341080B739708764DBD4DED6F
8790FD69C821B50404F50347080B9097
08764DA24A836F6B90F7693721BC040A
F7035A080BBE9708764DE347036F5F90
EB692D21BB0417F9036B080BE3970876
4D6645CE6E4690E7693421B40458FB03
74080BFC9708764D2943716E3190DD69
3E21B70478FD0387080B339808764DC5
409D6D1C90D069AB1FBA04B7FF038D08
0B749808764D3E3E376D0090C669A21F
B504C3020483080B949808764D593B0C
6DDC8FBA69A31FB1043F060480080BA8
9808764D5338DA6CB98FAB69A41FB704
16090476080BC29808774D4F35956CA5
8FA269F61DBA046E0B047B080BD29808
774D2F32796C7E8F9169FD1DBE04F30C
0487080BE99808784DBB2F156C678F88
69EF1DBC04900E048F080B109908784D
CF2D9B6B508F8569F51DB6046F1004A5
080B3D9908784D6F2CFE6A338F8C69DC
1DA704FA110435090B819908794D5D2B
706A0D8F8569E51D9F04671604F5090B
B69908794D6D2A006AF18E6669E41DAB
04E31D047F0A0BE699087A4D84298C69
D18E5369E61DA804B12404FF0A0B179A
087A4DB2283F69AD8E3C69031A9D047F
2A041D0B0B379A087A4DD727DC68868E
3369051AA804F32E047A0B0B5D9A087B
4DF6268C686B8E3369FA19A004693204
940B0B779A087A4D32266268498E2E69
051AA904A934047D0B0B8A9A087A4D98
2518681B8E2869031AA204CA3504540B
0BA99A087B4D1325B967F58D3569AA16
A504533604440B0BD49A087B4D9B243D
67C18D2D69A516A604A93604E30B0B05
9B087B4D4324BF66878D3B69A216A704
6A3804480C0B299B087A4DE72394663E
8D3569A916A204433B04480C0B449B08
7A4DA5233D660B8D3569D411C404963E
04680C0B699B087A4D5E23CC65CD8C38
69D511C9047C4104740C0B9D9B087A4D
28233E65928C3F69D311C60484430490
0C0BCC9B087A4D0023D864528C3E69CE
11C7049A45048F0C0BFF9B087A4DD622
4364198C4C69C80D0705174704960C0B
399C087A4DB422BA63D28B7369CB0D07
05D14704E50C0B769C08794D8F223D63
938BAB69D10D0A059549045D0D0B9C9C
08794D7B2205635C8BC969CD0D020558
4D04C90D0BC29C08794D572273621D8B
D2696711FA04655104B90E0BF69C087A
4D3F221262E58A4E6A6611F504045504
790F0B119D08794D32220862AE8AA46A
6011F504DD57049E0F0B1B9D087A4D12
22ED61728AE46A6211F804755804D70F
0B279D087A4D0222D761478A216B5510
F304DF5704B90F0B2D9D087A4D0222D4
611C8A4E6B5B10FA041357044B100B36
9D087B4DE821A961E489756B5C10F704
D05604D8100B419D087C4DD5219061B1
89986B5710F904C958045B110B4C9D08
7C4DC32178617889C26B670F0505F95B
0433120B549D087C4DAF2172613F89DE
6B600F09056D5E042C130B5A9D087C4D
A7216A610E89FE6B5E0F0705D96004F7
130B5F9D087C4D9D217061D9883C6C5A
0F050570630410150B669D087C4D9421
78619888A76C600F0E05D76504DD160B
6B9D087C4D89218C615588E96C580F1B
05D1670468170B6E9D087D4D7F218E61
0D881E6D550F2705E3680436180B709D
087D4D70219861D087536D550F200579
690442180B739D087E4D582199619387
926D5C0F1B05F36904DE170B739D087E
4D6B219B614387C96D7C0F1905076A04
1F170B749D087E4D58218861F786E56D
820F11057269045B160B769D087E4D52
218861AC86016E870F1A05D068041616
0B7A9D087E4D4721826173861F6E820F
0E0551680423160B779D087F4D3E2184
6139863F6E8A1086054568040A160B76
9D087F4D34215F610F865D6E86108605
7C6804F8150B759D087F4D2B213B61DA
856A6E871080058D6804E1150B789D08
7F4D2B214961AC858E6E8B1083058A68
04FA150B779D087F4D1C2132618E85BA
6EBD0F46058F6804DB150B759D087F4D
0D213C616385EA6EC10F4C05E26804F6
150B749D087F4D0E213D613F850D6FBB
0F45051E6904D1150B759D087F4D0B21
2A611E852F6FBD0F42050C690455150B
779D087F4D002138610585576F121036
055D680462150B709D087F4D00213F61
E584836F14103505A0670486150B289D
087F4DFA20DD62D384CF6F0F103405A3
6604B4100B379C087F4DEF20A566FC84
EE6F0C103505526004BB0D0B9C9A087F
4DF320896B3F85E86FBA0D2805A75204
C50B0BA598087F4DE22033708D85F26F
BE0D2905F53F04780A0BE996087F4DD4
206573ED852C70BF0D24050C28044809
0BCF9508804DCA204E7539867B70BE0D
2905A0110411090BA89408804DEA20BC
788786BD702215C104F70104BE080B16
9308804D83219F7CCF8686701A15C604
93F5035C080B919108804D5423627F12
8773702015C90415E7033F080B439008
804DB726A6824D8734702B15CB044EDC
036D080BC68E08814DD52A04868187F2
6FA217B40411D80343080B5E8D08814D
F02F9188AD87D26FA617B4041CD30323
080B1D8C08814D1436558BC887B06F9D
17B80464CA0307080BB98A08814DA63C
528EF6871370A317B90456C003E8070B
638908824D44438B901688C270FC169D
04CFB503EB070B3C8808824D2D494D93
3688FE70FB169304BAAE03F0070BE586
08824D8F4FAA9649881271F616960474
AB03EB070B938508824D7A562F996388
FD70FA169A04F1A703DF070B53840882
4D1E5E779B91882371F8169C0440A003
D6070BD98208824D83653AA0C8888A71
F2139704209703D7070B678108824DA5
6C20A20C890272F2139304939203D607
0B298008824D5C7246A44C894972F213
9304909003D4070BDE7E08824D0D78D9
A88F89C772EF139A04D68D03D6070BAB
7D08824DDA7DA9A5CF89F2726D0D8904
B78A03DA070BAF7C08814D298377AC34
8A3B6E6A0D8404FD8403DD070BF17B08
814D3B887FA98A8A246E6A0D8604637E
03DF070B937B08814D9E8C9BA6B58A19
726E0D8804747903E7070B747B08814D
BE90E3AAC68A7472DC0A6404497303EE
070B5E7B08814DF294FCB0068BB172D6
0A6804866D03EB070B127B08814D2099
9DB8588BEF72D80A60040A6A03E7070B
4F7A08814D159D5DB79A8BAB72D90A65
04DA6803E0070B637908814D98A10DB6
DE8BD16DAE096304E06803EE070B9F78
08814DABA50AB40E8C266EB2096804E5
6703E5070BC17708814DF2A8FFB05F8C
D66DAB096E04DB6403F6070BAF760881
4D96AB30AF8D8C436DAC096404666103
FA070B7E7508814D5DAD7BACC58CEB6C
AB096504115E03FA070B817408814DB2
AED2A6E88C546CAD077AFCF65B03F807
0B147408814D99AFE9AB1F8D726CAB07
7DFC335B03F6070B0C7408814DECAF81
A54D8D0771B1077FFCAF5B03F4070BCF
7308814D7FAF2FA3728DF970AF077DFC
7D5C03EE070BCB7308814D4BAE96939F
8DB07059095609235D03EA060BCA7308
814D9AAC90A4B28D4A745A095B09D55D
03AC030BCB7308814DDCAAB9A5EA8DFE
7060095F09905E0389030BCA7308814D
8AA9D89F2E8EDB705C095B097B5F0399
030BCA7308814D2BAA629A3B8EBF7142
FC8D036160038F030BCA7308814D53AB
9097448E157244FC8B034A610391030B
C97308814D01AC8B95548E577249FC8E
033A620310040BCA7308814DD4ABC28A
5B8E277341FC8E034F630379050BCA73
08824D74ABE289768E9B73390164041E
6403BB070BCA7308824D3BABE78C7E8E
AB7333016804A66503E1070BCA730882
4DB8AA25937D8E167336016B04906803
E2070BC97308824D9DA8DE966F8E8672
3D016804176B0361070BC87308834D38
A7CF9B538EA072C203FB03EE6C033B07
0BCA7308824D8EA6168E268E4A72C303
FE031E6E0308050BCA7308824D3FA5B8
AFD98D7071C603FF03F06E0387040BC9
7308824D78A2959D9F8D7F70C2030204
5F6F0354040BC87308824DA49E9AB478
8DA86FC003FE03E56F031F040BC77308
834D929A33B5378D1472A006D5026C70
03A6030BC77308844D81969FAF278C73
73A906CF020F7103A0030BCA7308844D
F9921BB4508B3072A406CA02DC710387
030BC77308844DCF8F5DACD58AC671A4
06CE02A1720388030BC67308844D718D
27959A8AC371B4027E0348730360030B
C87308844D918BD3938F8A5A71B40281
03BD730351030BC97308844DE5899095
948ADE70BB027C031474033C030BCA73
08834D9D888E94948A8870B9027A0362
740340030BC97308834D758788939B8A
9E70B2027B03AA740336030BC9730883
4D97860D939B8A7570B5027C03F07403
40030BC97308844DD985E592CD8A8E70
B4027903</Data>

   <DataCRC>f908509</DataCRC>

   <BytesSent>9108</BytesSent>

</SBEDataUpload>
</InstrumentRawData>
</SBEDataUploadFile>
